Workbook
Name _MO: 'Naming ranges'!$C$7:$C$13
Name Alphabets: 'Dependent dropdown'!$G$3:$G$10
Name antennas: 'Scenario manager'!$E$10
Name button: 'Scenario manager'!#REF!
Name charg.port: 'Scenario manager'!$E$9
Name cooling: 'Scenario manager'!$E$14
Name Digitizer: 'Scenario manager'!$E$5
Name GRADES: 'Data for dropdown'!$F$4:$F$10
Name mic: 'Scenario manager'!$E$7
Name MO: 'Naming ranges'!$C$9
Name Month: 'Naming ranges'!$C$7:$C$14
Name MONTHSPRODUCTS: 'Naming ranges'!$C$6:$E$14
Name NativeTimeline_Date: #N/A
Name Numbers: 'Dependent dropdown'!$H$3:$H$10
Name Product: 'Naming ranges'!$D$7:$D$14
Name Sales: #REF!
Name Sceen: 'Scenario manager'!#REF!
Name screen: 'Scenario manager'!$E$4
Name simtray: 'Scenario manager'!$E$11
Name Slicer_Products: #N/A
Name Slicer_Region: #N/A
Name speaker: 'Scenario manager'!$E$6
Name Symbols: 'Dependent dropdown'!$I$3:$I$10
Name Total: 'Data Table'!#REF!
Name Type_of_data: 'Dependent dropdown'!#REF!
Name vibr.motor: 'Scenario manager'!$E$13

Sheet Split (and freeze)
B2: Date | C2: Region | D2: Items | E2: Price | H2: Date | I2: Region | J2: Items | K2: Price
B3: 36531 | C3: East | D3: Footwear | E3: 12000 | H3: 36531 | I3: East | J3: Footwear | K3: 12000
B4: 36542 | C4: East | D4: Mobile | E4: 35700 | H4: 36542 | I4: East | J4: Mobile | K4: 35700
B5: 36535 | C5: East | D5: Mobile | E5: 42840 | H5: 36535 | I5: East | J5: Mobile | K5: 42840
B6: 36530 | C6: East | D6: Smartwatch | E6: 10000 | H6: 36530 | I6: East | J6: Smartwatch | K6: 10000
B7: 36531 | C7: East | D7: Smartwatch | E7: 30000 | H7: 36531 | I7: East | J7: Smartwatch | K7: 30000
B8: 36533 | C8: North | D8: Bass Headphones | E8: 32640 | H8: 36533 | I8: North | J8: Bass Headphones | K8: 32640
B9: 36526 | C9: North | D9: Beard trimmer | E9: 4000 | H9: 36526 | I9: North | J9: Beard trimmer | K9: 4000
B10: 36528 | C10: North | D10: Deodarant | E10: 8000 | H10: 36528 | I10: North | J10: Deodarant | K10: 8000
B11: 36544 | C11: North | D11: Deodarant | E11: 8000 | H11: 36544 | I11: North | J11: Deodarant | K11: 8000
B12: 36541 | C12: North | D12: Mobile | E12: 42840 | H12: 36541 | I12: North | J12: Mobile | K12: 42840
B13: 36545 | C13: North | D13: Shaving cream | E13: 8000 | H13: 36545 | I13: North | J13: Shaving cream | K13: 8000
B14: 36534 | C14: North | D14: Wrist watch | E14: 48960 | H14: 36534 | I14: North | J14: Wrist watch | K14: 48960
... B26: 36529 | C26: West | D26: Shaving cream | E26: 8000 | H26: 36529 | I26: West | J26: Shaving cream | K26: 8000
F32: 36538 | G32: South | H32: Earbuds
F33: 36537 | G33: South | H33: Jackets

Sheet FORMULAS AND FUNCTIONS
B2: Month | C2: Product | D2: Sales
B3: January | C3: Pencils | D3: 1000 | F3: 50 | G3: =SUM(F3,F5,F7,F9) -> 240 | H3: SUM | J3: COUNT | K3: =COUNT(G3:G8) -> 6
B4: February | C4: Books | D4: 5000 | E4: 40 | G4: =SUM(E4,E6,E8) -> 200 | H4: SUM | J4: COUNT | K4: =COUNT(C3:C9) -> 0
B5: March | C5: Colors | D5: 1000 | F5: 10 | G5: =AVERAGE(F3,F7,F9,F5) -> 60 | H5: AVERAGE
B6: April | C6: Highlighters | D6: 3500 | E6: 70 | G6: =AVERAGE(E4,E6,E8) -> 66.666667 | H6: AVERAGE | J6: COUNTA | K6: =COUNTA(H3:H8) -> 6
B7: May | C7: Scales/Rulers | D7: 3000 | F7: 80 | G7: =PRODUCT(E4,E6,E8) -> 252000 | H7: PRODUCT | J7: COUNTA | K7: =COUNTA(G3:H8) -> 12
B8: June | C8: Notebooks | D8: 4000 | E8: 90 | G8: =PRODUCT(F3,F5,F7) -> 40000 | H8: PRODUCT | J8: COUNTA | K8: =COUNTA(F3:H8) -> 15
B9: July | C9: Magazines | D9: 4000 | F9: 100
B10: Total | D10: =SUM(D3:D9) -> 21500 | E10: =SUM(E3:E9) -> 200 | J10: COUNTBLANK | K10: =COUNTBLANK(H3:H8) -> 0
J11: COUNTBLANK | K11: =COUNTBLANK(J3:J9) -> 2
C12: MINIMUM | D12: =MIN(D3:D9) -> 1000 | G12: MINIMUM | H12: =MIN(F3:F9) -> 10 | J12: COUNTBLANK | K12: =COUNTBLANK(D3:E9) -> 4
C13: MAXIMUM | D13: =MAX(D3:D9) -> 5000 | G13: MAXIMUM | H13: =MAX(F3:F9) -> 100

Sheet goto, go to special
B2: Month | C2: Product | D2: Sales
B3: January | C3: Pencils | D3: 1000 | F3: 10 | I3: =SUM(#REF!) -> #REF!
B4: February | C4: Books | D4: 5000 | F4: 90
B5: March | C5: Colors | D5: 1000 | F5: 70
B6: April | C6: Highlighters | D6: 3500 | F6: 50
B7: May | C7: Scales/Rulers | D7: 3000 | F7: 40 | I7: =SUM(#REF!) -> #REF!
B8: June | C8: Notebooks | D8: 4000 | F8: 23
B9: July | C9: Magazines | D9: 4000 | F9: 50
B10: Total | D10: =SUM(D3:D9) -> 21500 | F10: =SUM(F3:F9) -> 333
B13: {={"red","white","green"}} -> red | C13: white | D13: green
B18: SUSHANT SHARMA | C18: JOHN JACOBS
B20: aiYSHA SINHA | C20: ALISHA GADGE
B22: ARNAV KUMAR
C23: SUSHANT SHARMA
H30: fgh

Sheet find, replace
B2: Month | C2: Product | D2: Sales
B3: January | C3: Pens | D3: 1000 | F3: 100 | I3: =SUM(#REF!) -> #REF!
B4: February | C4: Pens | D4: 5000 | F4: 90
B5: March | C5: Colors | D5: 1000 | F5: 70
B6: April | C6: Highlighters | D6: 3500 | F6: 60
B7: May | C7: Scales/Rulers | D7: 3000 | F7: 40 | I7: =SUM(#REF!) -> #REF!
B8: June | C8: books | D8: 4000 | F8: 23
B9: August | C9: Magazines | D9: 4000 | F9: 60
B10: Total | D10: =SUM(D3:D9) -> 21500 | F10: =SUM(F3:F9) -> 443
F15: Magazines
D16: books
A17: Pens
I18: Pens
E23: February
C25: february
I26: August
D31: January
D32: February
D33: March
D34: April
D35: May
D36: June
D37: August
D38: Total

Sheet VIsible cells only
A1: Month | B1: Product | C1: Sales
A2: February | B2: Books | C2: 5000 | E2: 90
A3: April | B3: Highlighters | C3: 3500 | E3: 50
A4: June | B4: Notebooks | C4: 4000 | E4: 23
A5: July | B5: Magazines | C5: 4000 | E5: 50
A6: Total | C6: 21500 | E6: 333

Sheet FILL - down right flash
E2: 1 | F2: 2 | G2: 3 | H2: 4 | I2: 5 | J2: 6 | K2: 7 | L2: 8 | M2: 9 | N2: 10 | O2: 11 | P2: 12 | Q2: 13 | R2: 14 | S2: 15 | T2: 16 | U2: 17 | V2: 18 | W2: 19 | X2: 20 | Y2: 21 | Z2: 22 | AA2: 23 | AB2: 24 | AC2: 25 | AD2: 26 | AE2: 27 | AF2: 28 | AG2: 29 | AH2: 30 | AI2: 31 | AJ2: 32 | AK2: 33 | AL2: 34
E3: 2
E4: 3
E5: 4 | G5: but | H5: and | I5: not | J5: but | K5: and | L5: not | M5: but | N5: and | O5: not | P5: but | Q5: and | R5: not | S5: but | T5: and | U5: not | V5: but | W5: and | X5: not | Y5: but | Z5: and | AA5: not | AB5: but | AC5: and | AD5: not | AE5: but | AF5: and | AG5: not | AH5: but | AI5: and | AJ5: not
E6: 5 | G6: but
E7: 6 | G7: but | J7: 12
E8: 7 | G8: but
E9: 8 | G9: but
E10: 9 | G10: but
E11: 10 | G11: but
E12: 11 | G12: but
E13: 12 | G13: but
E14: 13 | G14: but
E15: 14 | G15: but
E16: 15 | G16: but
E17: 16
E18: 17
E19: 18
E20: 19
E21: 20
B22: Full Name | C22: First name | D22: Last Name | L22: 5 | M22: 5 | N22: 5 | O22: 5 | P22: 5 | Q22: 5 | R22: 5 | S22: 5 | T22: 5 | U22: 5 | V22: 5 | W22: 5 | X22: 5 | Y22: 5 | Z22: 5 | AA22: 5 | AB22: 5 | AC22: 5 | AD22: 5 | AE22: 5 | AF22: 5
B23: Steve Harvey | C23: Steve | D23: Harvey | L23: 5
B24: Reshma Malik | C24: Reshma | D24: Malik | L24: 5
B25: Garris Johnson | C25: Garris | D25: Johnson | L25: 5
B26: Sanjay Gupta | C26: Sanjay | D26: Gupta | L26: 5
B27: Harry Potter | C27: Harry | D27: Potter | L27: 5
B28: Arnav Tripathi | C28: Arnav | D28: Tripathi | E28: 123 | F28: 1 | G28: 2 | H28: 3 | L28: 5
B29: Sushma Sharma | C29: Sushma | D29: Sharma | E29: 234 | F29: 2 | G29: 3 | H29: 4 | J29: Monday | L29: 5
B30: Jacob Peter | C30: Jacob | D30: Peter | E30: 345 | F30: 3 | G30: 4 | H30: 5 | J30: Tuesday | L30: 5
B31: Alisha Sinha | C31: Alisha | D31: Sinha | E31: 456 | F31: 4 | G31: 5 | H31: 6 | J31: Wednesday | L31: 5
B32: Alex Samson | C32: Alex | D32: Samson | E32: 567 | F32: 5 | G32: 6 | H32: 7 | J32: Thursday | L32: 5
B33: Rajul Kaur | C33: Rajul | D33: Kaur | E33: 678 | F33: 6 | G33: 7 | H33: 8 | J33: Friday | L33: 5
B34: Rocky Pattinson | C34: Rocky | D34: Pattinson | E34: 789 | F34: 7 | G34: 8 | H34: 9 | J34: Saturday | L34: 5
B35: Harry Potter | C35: Harry | D35: Potter | E35: 890 | F35: 8 | G35: 9 | H35: 0 | J35: Sunday | L35: 5
B36: Arnav Tripathi | C36: Arnav | D36: Tripathi | J36: Monday | L36: 5
B37: Sushma Sharma | C37: Sushma | D37: Sharma | J37: Tuesday | L37: 5
B38: Jacob Peter | C38: Jacob | D38: Peter | J38: Wednesday | L38: 5
B39: Alisha Sinha | C39: Alisha | D39: Sinha | J39: Thursday | L39: 5
E40: skfdhsnkf | L40: 5
E41: skfdhsnkf | L41: 5
E42: skfdhsnkf | L42: 5
A43: skfdhsnkf | B43: skfdhsnkf | C43: skfdhsnkf | D43: skfdhsnkf | E43: skfdhsnkf | L43: 5
L44: 5
L45: 5
A46: 10 | L46: 5
A47: 20 | L47: 5
A48: 30 | L48: 5
A49: 40 | L49: 5
A50: 50 | D50: Month | E50: Product | F50: Sales | L50: 5
A51: 60 | D51: January | E51: Pencils | F51: 1000 | L51: 5
A52: 70 | D52: February | E52: Books | F52: 5000 | L52: 5
A53: 80 | D53: March | E53: Colors | F53: 1000 | L53: 5
A54: 90 | D54: April | E54: Highlighters | F54: 3500 | L54: 5
A55: 100 | D55: May | E55: Scales/Rulers | F55: 3000 | L55: 5
D56: June | E56: Notebooks | F56: 4000
D57: July | E57: Magazines | F57: 4000
D58: Total | F58: =SUM(F51:F57) -> 21500

Sheet Copying formulas
C2: Items | D2: Price | F2: Items | G2: Price
C3: Beard trimmer | D3: 4000 | F3: Jackets | G3: 6000 | J3: 1
C4: Hair dryer | D4: 9000 | F4: Earbuds | G4: 35700 | J4: 2
C5: Deodarant | D5: 8000 | F5: Bass Headphones | G5: 32640 | J5: 3
C6: Shaving cream | D6: 8000 | F6: Wrist watch | G6: 48960 | J6: 4
C7: Smartwatch | D7: 10000 | F7: Mobile | G7: 42840 | J7: 5
C8: Footwear | D8: 12000 | F8: Mobile | G8: 35700 | J8: =SUM(G3:G8) -> 201840
C9: TOTAL | D9: XSUM(D3:D8) | F9: TOTAL | G9: =SUM(G3:G8) -> 201840
C10: AVERAGE | D10: XAVERAGE(D3:D8) | F10: AVERAGE | G10: =AVERAGE(G3:G8) -> 33640
C11: MIN | D11: XMIN(D3:D8) | F11: MIN | G11: =MIN(G3:G8) -> 6000 | I11: =SUM(G3:G8) -> 201840
C13: Earbuds | D13: 35700 | F13: Hair dryer | G13: 9000 | J13: =SUM(G3:G8) -> 201840
C14: Bass Headphones | D14: 32640 | F14: Deodarant | G14: 8000 | J14: =AVERAGE(G3:G8) -> 33640
C15: Wrist watch | D15: 48960 | F15: Shaving cream | G15: 8000 | J15: =MIN(D3:D8) -> 4000
C16: Mobile | D16: 42840 | F16: Smartwatch | G16: 10000
C17: Beard trimmer | D17: 4000 | F17: Mobile | G17: 35700 | I17: =SUM(D3:D8) -> 51000
C18: TOTAL | D18: =SUM(D12:D17) -> 164140 | F18: TOTAL | G18: =SUM(G12:G17) -> 70700 | I18: =AVERAGE(D3:D8) -> 8500
C19: AVERAGE | D19: =AVERAGE(D12:D17) -> 32828 | F19: AVERAGE | G19: =AVERAGE(G12:G17) -> 14140 | I19: =MIN(D3:D8) -> 4000
C20: MIN | D20: =MIN(D12:D17) -> 4000 | F20: MIN | G20: =MIN(G12:G17) -> 8000
D24: Items | E24: Selling Price (Revenue) | F24: Cost Price (Expenses) | G24: Profit | H24: Profit %age
D25: Jackets | E25: 9000 | F25: 1000 | G25: =IMSUB(E25,F25) -> 8000 | H25: =G25/F25 -> 8
D26: Earbuds | E26: 8000 | F26: 2000 | G26: =IMSUB(E26,F26) -> 6000 | H26: =G26/F26 -> 3
D27: Bass Headphones | E27: 8000 | F27: 4000 | G27: =IMSUB(E27,F27) -> 4000 | H27: =G27/F27 -> 1
D28: Wrist watch | E28: 10000 | F28: 3000 | G28: =IMSUB(E28,F28) -> 7000 | H28: =G28/F28 -> 2.3333333
D29: Mobile | E29: 35700 | F29: 10000 | G29: =IMSUB(E29,F29) -> 25700 | H29: =G29/F29 -> 2.57
D30: TOTAL | E30: =SUM(E25:E29) -> 70700 | F30: =SUM(F25:F29) -> 20000 | G30: =IMSUM(G25:G29) -> 50700
D31: AVERAGE | E31: =AVERAGE(E25:E29) -> 14140 | F31: =AVERAGE(F25:F29) -> 4000
D32: MIN | E32: =MIN(E25:E29) -> 8000 | F32: =MIN(F25:F29) -> 1000

Sheet SUBTOTAL
B2: Date | C2: Region | D2: Items | E2: Price
B3: 36530 | C3: East | D3: Smartwatch | E3: 10000
B4: 36531 | C4: East | D4: Footwear | E4: 12000
B5: 36542 | C5: East | D5: Mobile | E5: 35700
B6: 36535 | C6: East | D6: Mobile | E6: 42840
C7: East Total | E7: =SUBTOTAL(9,E3:E6) -> 100540
B8: 36526 | C8: North | D8: Beard trimmer | E8: 4000
B9: 36528 | C9: North | D9: Deodarant | E9: 8000
B10: 36544 | C10: North | D10: Deodarant | E10: 8000
B11: 36545 | C11: North | D11: Shaving cream | E11: 8000
B12: 36533 | C12: North | D12: Bass Headphones | E12: 32640
B13: 36541 | C13: North | D13: Mobile | E13: 42840
B14: 36534 | C14: North | D14: Wrist watch | E14: 48960
C15: North Total | E15: =SUBTOTAL(9,E8:E14) -> 152440
B16: 36537 | C16: South | D16: Jackets | E16: 6000
B17: 36546 | C17: South | D17: Smartwatch | E17: 10000
B18: 36539 | C18: South | D18: Bass Headphones | E18: 32640
B19: 36538 | C19: South | D19: Earbuds | E19: 35700
B20: 36540 | C20: South | D20: Wrist watch | E20: 48960
C21: South Total | E21: =SUBTOTAL(9,E16:E20) -> 133300
B22: 36536 | C22: West | D22: Beard trimmer | E22: 4000
B23: 36529 | C23: West | D23: Shaving cream | E23: 8000
B24: 36527 | C24: West | D24: Hair dryer | E24: 9000
B25: 36543 | C25: West | D25: Hair dryer | E25: 9000
B26: 36532 | C26: West | D26: Earbuds | E26: 35700
B27: 36547 | C27: West | D27: Mobile | E27: 35700
C28: West Total | E28: =SUBTOTAL(9,E22:E27) -> 101400
B29: TOTAL | E29: =SUM(E3:E27) -> 873960
C30: Grand Total | E30: =SUBTOTAL(9,E3:E29) -> 1361640
B36: Date | C36: Region | D36: Items | E36: Price
B37: 36531 | C37: East | D37: Footwear | E37: 12000
B38: 36542 | C38: East | D38: Mobile | E38: 35700
B39: 36535 | C39: East | D39: Mobile | E39: 42840
B40: 36530 | C40: East | D40: Smartwatch | E40: 10000
B42: 36533 | C42: North | D42: Bass Headphones | E42: 32640
B43: 36526 | C43: North | D43: Beard trimmer | E43: 4000
B44: 36528 | C44: North | D44: Deodarant | E44: 8000
B45: 36544 | C45: North | D45: Deodarant | E45: 8000
B46: 36541 | C46: North | D46: Mobile | E46: 42840
B47: 36545 | C47: North | D47: Shaving cream | E47: 8000
B48: 36534 | C48: North | D48: Wrist watch | E48: 48960
B50: 36539 | C50: South | D50: Bass Headphones | E50: 32640
... B61: 36529 | C61: West | D61: Shaving cream | E61: 8000
B63: TOTAL
B64: SUBTOTAL
C65: Grand Average

Sheet ROUND FUNCTIONS
B2: FUNCTIONS / NUMBERS | C2: 163.4 | D2: 123.7 | E2: 133.68 | F2: 55.77 | G2: 67.345 | H2: 89.123 | I2: 12.4843 | J2: 25.7654
B3: ROUND (upto 0 decimal place) | C3: =ROUND(C2,0) -> 163 | D3: =ROUND(D2,0) -> 124 | E3: =ROUND(E2,0) -> 134 | F3: =ROUND(F2,0) -> 56 | G3: =ROUND(G2,0) -> 67 | H3: =ROUND(H2,0) -> 89 | I3: =ROUND(I2,0) -> 12 | J3: =ROUND(J2,0) -> 26
B4: ROUND (upto 1 decimal place) | C4: =ROUND(C2,1) -> 163.4 | D4: =ROUND(D2,1) -> 123.7 | E4: =ROUND(E2,1) -> 133.7 | F4: =ROUND(F2,1) -> 55.8 | G4: =ROUND(G2,1) -> 67.3 | H4: =ROUND(H2,1) -> 89.1 | I4: =ROUND(I2,1) -> 12.5 | J4: =ROUND(J2,1) -> 25.8
B5: ROUND (upto 2 decimal place) | C5: =ROUND(C2,2) -> 163.4 | D5: =ROUND(D2,2) -> 123.7 | E5: =ROUND(E2,2) -> 133.68 | F5: =ROUND(F2,2) -> 55.77 | G5: =ROUND(G2,2) -> 67.35 | H5: =ROUND(H2,2) -> 89.12 | I5: =ROUND(I2,2) -> 12.48 | J5: =ROUND(J2,2) -> 25.77
B6: ROUND (upto 3 decimal place) | C6: =ROUND(C2,3) -> 163.4 | D6: =ROUND(D2,3) -> 123.7 | E6: =ROUND(E2,3) -> 133.68 | F6: =ROUND(F2,3) -> 55.77 | G6: =ROUND(G2,3) -> 67.345 | H6: =ROUND(H2,3) -> 89.123 | I6: =ROUND(I2,3) -> 12.484 | J6: =ROUND(J2,3) -> 25.765
B8: ROUNDUP (upto 0 decimal place) | C8: =ROUNDUP(C2,0) -> 164 | D8: =ROUNDUP(D2,0) -> 124 | E8: =ROUNDUP(E2,0) -> 134 | F8: =ROUNDUP(F2,0) -> 56 | G8: =ROUNDUP(G2,0) -> 68 | H8: =ROUNDUP(H2,0) -> 90 | I8: =ROUNDUP(I2,0) -> 13 | J8: =ROUNDUP(J2,0) -> 26
B9: ROUNDUP (upto 1 decimal place) | C9: =ROUNDUP(C2,1) -> 163.4 | D9: =ROUNDUP(D2,1) -> 123.7 | E9: =ROUNDUP(E2,1) -> 133.7 | F9: =ROUNDUP(F2,1) -> 55.8 | G9: =ROUNDUP(G2,1) -> 67.4 | H9: =ROUNDUP(H2,1) -> 89.2 | I9: =ROUNDUP(I2,1) -> 12.5 | J9: =ROUNDUP(J2,1) -> 25.8
B10: ROUNDUP (upto 2 decimal place) | C10: =ROUNDUP(C2,2) -> 163.4 | D10: =ROUNDUP(D2,2) -> 123.7 | E10: =ROUNDUP(E2,2) -> 133.68 | F10: =ROUNDUP(F2,2) -> 55.77 | G10: =ROUNDUP(G2,2) -> 67.35 | H10: =ROUNDUP(H2,2) -> 89.13 | I10: =ROUNDUP(I2,2) -> 12.49 | J10: =ROUNDUP(J2,2) -> 25.77
B11: ROUNDUP (upto 3 decimal place) | C11: =ROUNDUP(C2,3) -> 163.4 | D11: =ROUNDUP(D2,3) -> 123.7 | E11: =ROUNDUP(E2,3) -> 133.68 | F11: =ROUNDUP(F2,3) -> 55.77 | G11: =ROUNDUP(G2,3) -> 67.345 | H11: =ROUNDUP(H2,3) -> 89.123 | I11: =ROUNDUP(I2,3) -> 12.485 | J11: =ROUNDUP(J2,3) -> 25.766
B13: ROUNDDOWN (upto 0 decimal place) | C13: =ROUNDDOWN(C2,0) -> 163 | D13: =ROUNDDOWN(D2,0) -> 123 | E13: =ROUNDDOWN(E2,0) -> 133 | F13: =ROUNDDOWN(F2,0) -> 55 | G13: =ROUNDDOWN(G2,0) -> 67 | H13: =ROUNDDOWN(H2,0) -> 89 | I13: =ROUNDDOWN(I2,0) -> 12 | J13: =ROUNDDOWN(J2,0) -> 25
B14: ROUNDDOWN(upto 1 decimal place) | C14: =ROUNDDOWN(C2,1) -> 163.4 | D14: =ROUNDDOWN(D2,1) -> 123.7 | E14: =ROUNDDOWN(E2,1) -> 133.6 | F14: =ROUNDDOWN(F2,1) -> 55.7 | G14: =ROUNDDOWN(G2,1) -> 67.3 | H14: =ROUNDDOWN(H2,1) -> 89.1 | I14: =ROUNDDOWN(I2,1) -> 12.4 | J14: =ROUNDDOWN(J2,1) -> 25.7
B15: ROUNDDOWN(upto 2 decimal place) | C15: =ROUNDDOWN(C2,2) -> 163.4 | D15: =ROUNDDOWN(D2,2) -> 123.7 | E15: =ROUNDDOWN(E2,2) -> 133.68 | F15: =ROUNDDOWN(F2,2) -> 55.77 | G15: =ROUNDDOWN(G2,2) -> 67.34 | H15: =ROUNDDOWN(H2,2) -> 89.12 | I15: =ROUNDDOWN(I2,2) -> 12.48 | J15: =ROUNDDOWN(J2,2) -> 25.76
B16: ROUNDDOWN (upto 3 decimal place) | C16: =ROUNDDOWN(C2,3) -> 163.4 | D16: =ROUNDDOWN(D2,3) -> 123.7 | E16: =ROUNDDOWN(E2,3) -> 133.68 | F16: =ROUNDDOWN(F2,3) -> 55.77 | G16: =ROUNDDOWN(G2,3) -> 67.345 | H16: =ROUNDDOWN(H2,3) -> 89.123 | I16: =ROUNDDOWN(I2,3) -> 12.484 | J16: =ROUNDDOWN(J2,3) -> 25.765
B18: MROUND (multiple of 10) | C18: =MROUND(C2,10) -> 160 | D18: =MROUND(D2,10) -> 120 | E18: =MROUND(E2,10) -> 130 | F18: =MROUND(F2,10) -> 60 | G18: =MROUND(G2,10) -> 70 | H18: =MROUND(H2,10) -> 90 | I18: =MROUND(I2,10) -> 10 | J18: =MROUND(J2,10) -> 30
B19: MROUND (multiple of 7) | C19: =MROUND(C2,7) -> 161 | D19: =MROUND(D2,7) -> 126 | E19: =MROUND(E2,7) -> 133 | F19: =MROUND(F2,7) -> 56 | G19: =MROUND(G2,7) -> 70 | H19: =MROUND(H2,7) -> 91 | I19: =MROUND(I2,7) -> 14 | J19: =MROUND(J2,7) -> 28
B20: MROUND (multiple of 3) | C20: =MROUND(C2,3) -> 162 | D20: =MROUND(D2,3) -> 123 | E20: =MROUND(E2,3) -> 135 | F20: =MROUND(F2,3) -> 57 | G20: =MROUND(G2,3) -> 66 | H20: =MROUND(H2,3) -> 90 | I20: =MROUND(I2,3) -> 12 | J20: =MROUND(J2,3) -> 27
B21: MROUND (multiple of 2) | C21: =MROUND(C2,2) -> 164 | D21: =MROUND(D2,2) -> 124 | E21: =MROUND(E2,2) -> 134 | F21: =MROUND(F2,2) -> 56 | G21: =MROUND(G2,2) -> 68 | H21: =MROUND(H2,2) -> 90 | I21: =MROUND(I2,2) -> 12 | J21: =MROUND(J2,2) -> 26

Sheet Text functions
B3: NAMES | C3: UPPER | D3: LOWER | E3: PROPER | F3: LEFT | G3: RIGHT | H3: MID
B4: Ananya Pandey | C4: =UPPER(B4) -> ANANYA PANDEY | D4: =LOWER(B4) -> ananya pandey | E4: =PROPER(B4) -> Ananya Pandey | F4: =LEFT(B4, 5) -> Anany | G4: =RIGHT(B4, 5) -> andey | H4: =MID(B4, 2, 3) -> nan
B5: Arohi Sharma | C5: =UPPER(B5) -> AROHI SHARMA | D5: =LOWER(B5) -> arohi sharma | E5: =PROPER(B5) -> Arohi Sharma | F5: =LEFT(B5, 8) -> Arohi Sh | G5: =RIGHT(B5, 8) -> i Sharma | H5: =MID(B5, 3, 5) -> ohi S
B6: Mohandas Karamchand Gandhi | C6: =UPPER(B6) -> MOHANDAS KARAMCHAND GANDHI | D6: =LOWER(B6) -> mohandas karamchand gandhi | E6: =PROPER(B6) -> Mohandas Karamchand Gandhi | F6: =LEFT(B6, 8) -> Mohandas | G6: =RIGHT(B6, 8) -> d Gandhi | H6: =MID(B6, 3, 5) -> handa
B7: Milind Kumar Kalra | C7: =UPPER(B7) -> MILIND KUMAR KALRA | D7: =LOWER(B7) -> milind kumar kalra | E7: =PROPER(B7) -> Milind Kumar Kalra | F7: =LEFT(B7, 8) -> Milind K | G7: =RIGHT(B7, 8) -> ar Kalra | H7: =MID(B7, 3, 5) -> lind
B8: Anshu Poonawala | C8: =UPPER(B8) -> ANSHU POONAWALA | D8: =LOWER(B8) -> anshu poonawala | E8: =PROPER(B8) -> Anshu Poonawala | F8: =LEFT(B8, 8) -> Anshu Po | G8: =RIGHT(B8, 8) -> oonawala | H8: =MID(B8, 3, 5) -> shu P
B9: Rahul Singh Sharma | C9: =UPPER(B9) -> RAHUL SINGH SHARMA | D9: =LOWER(B9) -> rahul singh sharma | E9: =PROPER(B9) -> Rahul Singh Sharma | F9: =LEFT(B9, 8) -> Rahul Si | G9: =RIGHT(B9, 8) -> h Sharma | H9: =MID(B9, 3, 5) -> hul S
B10: Neil Armstrong | C10: =UPPER(B10) -> NEIL ARMSTRONG | D10: =LOWER(B10) -> neil armstrong | E10: =PROPER(B10) -> Neil Armstrong | F10: =LEFT(B10, 8) -> Neil Arm | G10: =RIGHT(B10, 8) -> rmstrong | H10: =MID(B10, 3, 5) -> il Ar
B11: Avnish Agrawal | C11: =UPPER(B11) -> AVNISH AGRAWAL | D11: =LOWER(B11) -> avnish agrawal | E11: =PROPER(B11) -> Avnish Agrawal | F11: =LEFT(B11, 8) -> Avnish A | G11: =RIGHT(B11, 8) -> Agrawal | H11: =MID(B11, 3, 5) -> nish
B12: Shashank Khan | C12: =UPPER(B12) -> SHASHANK KHAN | D12: =LOWER(B12) -> shashank khan | E12: =PROPER(B12) -> Shashank Khan | F12: =LEFT(B12, 8) -> Shashank | G12: =RIGHT(B12, 8) -> ank Khan | H12: =MID(B12, 3, 5) -> ashan
B16: NAMES | C16: LENGTH | D16: TRIM | E16: LENGTH | F16: FIND | G16: SEARCH
B17: Ananya Pandey | C17: =LEN(B17) -> 17 | D17: =TRIM(B17) -> Ananya Pandey | E17: =LEN(D17) -> 13 | F17: =FIND("y", D17, 7) -> 13 | G17: =SEARCH("y", D17, 7) -> 13
B18: Arohi Sharma | C18: =LEN(B18) -> 19 | D18: =TRIM(B18) -> Arohi Sharma | E18: =LEN(D18) -> 12 | F18: =FIND("r", D18, 5) -> 10 | G18: =SEARCH("r", D18, 5) -> 10
B19: Mohandas Karamchand G andhi | C19: =LEN(B19) -> 33 | D19: =TRIM(B19) -> Mohandas Karamchand G andhi | E19: =LEN(D19) -> 27 | F19: =FIND("M", D19) -> 1 | G19: =SEARCH("M", D19) -> 1
B20: Milind Kalra | C20: =LEN(B20) -> 27 | D20: =TRIM(B20) -> Milind Kalra | E20: =LEN(D20) -> 12 | F20: =FIND("l", D20) -> 3 | G20: =SEARCH("l",D20) -> 3
B21: Anshu Poonawala | C21: =LEN(B21) -> 30 | D21: =TRIM(B21) -> Anshu Poonawala | E21: =LEN(D21) -> 15 | F21: =FIND("o", D21) -> 8 | G21: =SEARCH("o", D21) -> 8
B22: Rahul Singh Sharma | C22: =LEN(B22) -> 24 | D22: =TRIM(B22) -> Rahul Singh Sharma | E22: =LEN(D22) -> 18 | F22: =FIND("g", D22) -> 10 | G22: =SEARCH("g", E22) -> #VALUE!
B23: Neil Armstrong | C23: =LEN(B23) -> 18 | D23: =TRIM(B23) -> Neil Armstrong | E23: =LEN(D23) -> 14 | F23: =FIND("g", D23) -> 14 | G23: =SEARCH("g", E23) -> #VALUE!
B24: Avnish Agrawal | C24: =LEN(B24) -> 14 | D24: =TRIM(B24) -> Avnish Agrawal | E24: =LEN(D24) -> 14 | F24: =FIND("g", D24) -> 9 | G24: =SEARCH("g", E24) -> #VALUE!
B25: Shashank Khan | C25: =LEN(B25) -> 18 | D25: =TRIM(B25) -> Shashank Khan | E25: =LEN(D25) -> 13 | F25: =FIND("K", D25) -> 10 | G25: =SEARCH("K", E25) -> #VALUE!
C28: NAMES | D28: SUBSTITUTE | E28: REPLACE
C29: Ananya Pandey | D29: =SUBSTITUTE(C29, "an", "Po") -> AnPoya PPodey | E29: =REPLACE(C29, 1, 5, "Po") -> Poa Pandey
C30: Arohi Sharma | D30: =SUBSTITUTE(C30, "rohi", "tul") -> Atul Sharma | E30: =REPLACE(C30, 1, 5, "Tul") -> Tul Sharma
C31: Mohandas Karamchand Gandhi | D31: =SUBSTITUTE(C31, "das", "tul") -> Mohantul Karamchand Gandhi | E31: =REPLACE(C31, 1, 5, "Tul") -> Tuldas Karamchand Gandhi
C32: Milind Kumar Kalra | D32: =SUBSTITUTE(C32, "lind", "tul") -> Mitul Kumar Kalra | E32: =REPLACE(C32, 1, 5, "Tul") -> Tuld Kumar Kalra
C33: Anshu Poonawala | D33: =SUBSTITUTE(C33, "oona", "tul") -> Anshu Ptulwala | E33: =REPLACE(C33, 1, 5, "Tul") -> Tul Poonawala
C34: Rahul Singh Sharma | D34: =SUBSTITUTE(C34, "Rahul", "tul") -> tul Singh Sharma | E34: =REPLACE(C34, 1, 5, "Tul") -> Tul Singh Sharma
C35: Neil Armstrong | D35: =SUBSTITUTE(C35, "strong", "tul") -> Neil Armtul | E35: =REPLACE(C35, 1, 5, "Tul") -> TulArmstrong
C36: Avnish Agrawal | D36: =SUBSTITUTE(C36, "wal", "tul") -> Avnish Agratul | E36: =REPLACE(C36, 1, 5, "Tul") -> Tulh Agrawal
C37: Shashank Khan | D37: =SUBSTITUTE(C37, "ank", "tul") -> Shashtul Khan | E37: =REPLACE(C37, 1, 5, "Tul") -> Tulank Khan
C39: You don't always know what you don't know. | D39: =SUBSTITUTE(C39, "know", "have", 1) -> You don't always have what you don't know. | E39: =REPLACE(C39, 8, 5, "have") -> You donhaveways know what you don't know.
D40: =SUBSTITUTE(C39, "know", "have", 2) -> You don't always know what you don't have. | E40: =REPLACE("know", 2, 2, "have") -> khavew
G41: CONCATENATE
E42: abc | F42: xyz | G42: =_xlfn.CONCAT(E42, " ", F42) -> abc xyz
E43: def | F43: uvw | G43: =_xlfn.CONCAT(E43, " & ", F43) -> def & uvw
E44: 123 | F44: 456 | G44: =_xlfn.CONCAT(E44, " - ", F44) -> 123 - 456
E45: 567 | F45: 789 | G45: =_xlfn.CONCAT(E45, " * ", F45) -> 567 * 789
E46: 567 | F46: xyz | G46: =_xlfn.CONCAT(E46, " @ ", F46) -> 567 @ xyz

Sheet Basic formatting
B2: Date | C2: Region | D2: Items | E2: Price
B3: 37262 | C3: East | D3: Footwear | E3: 12002
B4: 37273 | C4: East | D4: Mobile | E4: 35700 | G4: 0.92013889 | H4: 37257
B5: 37266 | C5: East | D5: Mobile | E5: 42840
B6: 37261 | C6: East | D6: Smartwatch | E6: 10000 | H6: D | I6: 1 | J6: 12
B7: 37262 | C7: East | D7: Smartwatch | E7: 30000 | H7: M | I7: 3 | J7: 12
B8: 37264 | C8: North | D8: Bass Headphones | E8: 32640 | H8: DD | I8: 01
B9: 37257 | C9: North | D9: Beard trimmer | E9: 4000 | H9: MM | I9: 02
B10: 37259 | C10: North | D10: Deodarant | E10: 8000 | H10: DDD | I10: Wed
B11: 37275 | C11: North | D11: Deodarant | E11: 8000 | H11: MMM | I11: Feb
B12: 37272 | C12: North | D12: Mobile | E12: 42840 | H12: DDDD | I12: Wednesday
B13: 37276 | C13: North | D13: Shaving cream | E13: 8000 | H13: MMMM | I13: February
B14: 37265 | C14: North | D14: Wrist watch | E14: 48960 | H14: YY | I14: 20
B15: 37270 | C15: South | D15: Bass Headphones | E15: 32640 | H15: YYYY | I15: 2020
B16: 37271 | C16: South | D16: Bass Headphones | E16: 42002
B17: 37269 | C17: South | D17: Earbuds | E17: 35700
B18: 37268 | C18: South | D18: Jackets | E18: 6000 | G18: 37262 | H18: dd/mm/yy
B19: 37277 | C19: South | D19: Smartwatch | E19: 10000 | G19: 37273 | H19: mm/dd/yy
B20: 37271 | C20: South | D20: Wrist watch | E20: 48960 | G20: 37266 | H20: dddd/mm/yy
B21: 37267 | C21: West | D21: Beard trimmer | E21: 4000 | G21: 37261 | H21: dddd/mmmm/yyyy
B22: 37263 | C22: West | D22: Earbuds | E22: 35700 | G22: 37262 | H22: dd-mm-yyyy-dddd
B23: 37258 | C23: West | D23: Hair dryer | E23: 7000 | G23: 37264
B24: 37274 | C24: West | D24: Hair dryer | E24: 9000 | G24: 37257 | H24: 37262
B25: 37278 | C25: West | D25: Mobile | E25: 35700 | G25: 37250
B26: 37260 | C26: West | D26: Shaving cream | E26: 8000 | G26: 37243
G27: 37236
G28: 37229

Sheet Logical operators (test)
B2: Date | C2: Region | D2: Items | E2: Price | J2: Comparative / Logical operators
B3: 36531 | C3: East | D3: Footwear | E3: 12000 | J3: =
B4: 36542 | C4: East | D4: Mobile | E4: 35700 | J4: >
B5: 36535 | C5: East | D5: Mobile | E5: 42840 | J5: <
B6: 36530 | C6: East | D6: Smartwatch | E6: 10000 | F6: =E4>E11 -> FALSE | G6: =D3>D9 -> TRUE | J6: >=
B7: 36533 | C7: North | D7: Bass Headphones | E7: 32640 | F7: =E4<E11 -> TRUE | G7: =D9<D11 -> TRUE | J7: <=
B8: 36526 | C8: North | D8: Beard trimmer | E8: 4000 | F8: =E10=E9 -> TRUE | G8: =D8>=D13 -> FALSE | J8: <>
B9: 36528 | C9: North | D9: Deodarant | E9: 8000 | F9: =E4>=E11 -> FALSE | G9: =D16<=D15 -> FALSE
B10: 36544 | C10: North | D10: Deodarant | E10: 8000 | F10: =E4<=E11 -> TRUE | G10: =D9=D4 -> FALSE
B11: 36541 | C11: North | D11: Mobile | E11: 42840 | F11: =E9<>E12 -> FALSE | G11: =D9=D10 -> TRUE
B12: 36545 | C12: North | D12: Shaving cream | E12: 8000 | F12: =E7<>E13 -> TRUE | G12: =D12<>D14 -> TRUE
B13: 36534 | C13: North | D13: Wrist watch | E13: 48960
B14: 36539 | C14: South | D14: Bass Headphones | E14: 32640
B15: 36538 | C15: South | D15: Earbuds | E15: 35700
B16: 36537 | C16: South | D16: Jackets | E16: 6000
B17: 36546 | C17: South | D17: Smartwatch | E17: 10000
B18: 36540 | C18: South | D18: Wrist watch | E18: 48960
B19: 36536 | C19: West | D19: Beard trimmer | E19: 4000
B20: 36532 | C20: West | D20: Earbuds | E20: 35700
B21: 36527 | C21: West | D21: Hair dryer | E21: 9000
B22: 36543 | C22: West | D22: Hair dryer | E22: 9000
B23: 36547 | C23: West | D23: Mobile | E23: 35700
B24: 36529 | C24: West | D24: Shaving cream | E24: 8000

Sheet How to use IF functions
C3: Date | D3: Region | E3: Items | F3: Price
C4: 36531 | D4: East | E4: Footwear | F4: 12000 | I4: No
C5: 36542 | D5: East | E5: Mobile | F5: 35700 | I5: Yes
C6: 36535 | D6: East | E6: Mobile | F6: 42840 | I6: Yes, No
C7: 36530 | D7: East | E7: Smartwatch | F7: 10000 | I7: 10, 20
C8: 36533 | D8: North | E8: Bass Headphones | F8: 32640 | I8: YES, NO
C9: 36526 | D9: North | E9: Beard trimmer | F9: 4000 | I9: Expensive, Inexpensive
C10: 36528 | D10: North | E10: Deodarant | F10: 8000
C11: 36544 | D11: North | E11: Deodarant | F11: 8000 | H11: =IF(F4>F5, "Yes", "No") -> No
C12: 36541 | D12: North | E12: Mobile | F12: 42840 | H12: =IF(F4<F5, "Yes", "No") -> Yes
C13: 36545 | D13: North | E13: Shaving cream | F13: 8000 | H13: =IF(F8>F14, 10, 20) -> 20
C14: 36534 | D14: North | E14: Wrist watch | F14: 48960 | H14: =IF(F9<F15, 10, 20) -> 10
C15: 36539 | D15: South | E15: Bass Headphones | F15: 32640 | H15: =IF(F7=F18, "YES", "NO") -> YES
C16: 36538 | D16: South | E16: Earbuds | F16: 35700 | H16: =IF(F18=F7, UPPER(I5), UPPER(I4)) -> YES
C17: 36537 | D17: South | E17: Jackets | F17: 6000 | H17: =IF(F21<>F19, "Expensive", "Inexpensive") -> Expensive
C18: 36546 | D18: South | E18: Smartwatch | F18: 10000 | H18: =IF(F21>F19, "Expensive", "Inexpensive") -> Inexpensive
C19: 36540 | D19: South | E19: Wrist watch | F19: 48960
C20: 36536 | D20: West | E20: Beard trimmer | F20: 4000
C21: 36532 | D21: West | E21: Earbuds | F21: 35700
C22: 36527 | D22: West | E22: Hair dryer | F22: 9000
C23: 36543 | D23: West | E23: Hair dryer | F23: 9000
C24: 36547 | D24: West | E24: Mobile | F24: 35700
C25: 36529 | D25: West | E25: Shaving cream | F25: 8000

Sheet Absolute Relative cell referenc
B3: Items | C3: Selling Price (Revenue) | D3: Cost Price (Expenses) | E3: Profit (SP - CP) | F3: Profit (SP - CP (10000)) | G3: Profit/50
B4: Jackets | C4: 20000 | D4: 1000 | E4: =IMSUB(C4,D4) -> 19000 | F4: =C4-$E$13 -> 10000 | G4: =F4/$E$12 -> 200
B5: Earbuds | C5: 11000 | D5: 2000 | E5: =IMSUB(C5,D5) -> 9000 | F5: =C5-$E$13 -> 1000 | G5: =F5/$E$12 -> 20
B6: Bass Headphones | C6: 11000 | D6: 4000 | E6: =IMSUB(C6,D6) -> 7000 | F6: =C6-$E$13 -> 1000 | G6: =F6/$E$12 -> 20
B7: Wrist watch | C7: 10000 | D7: 3000 | E7: =IMSUB(C7,D7) -> 7000 | F7: =C7-$E$13 -> 0 | G7: =F7/$E$12 -> 0
B8: Mobile | C8: 35000 | D8: 10000 | E8: =IMSUB(C8,D8) -> 25000 | F8: =C8-$E$13 -> 25000 | G8: =F8/$E$12 -> 500
B9: TOTAL | C9: =SUM(C4:C8) -> 87000 | D9: =SUM(D4:D8) -> 20000
C12: Divide by | E12: 50
C13: Cost Price (Expense) | E13: 10000

Sheet If functions 
C2: Date | D2: Region | E2: Items | F2: Price
C3: 36531 | D3: East | E3: Footwear | F3: 12000 | H3: SUMIF | I3: AVERAGEIF | J3: NESTEDIF
C4: 36542 | D4: East | E4: Mobile | F4: 35700 | H4: =SUMIF(D3:D24, "East", F3:F24) -> 100540 | I4: =AVERAGEIF(D3:D24, "west", F3:F24) -> 11450 | J4: =IF(F3>F11, "YES", IF(F14<F15, "True")) -> True
C5: 36535 | D5: East | E5: Mobile | F5: 42840 | J5: =IF(F8=F10, "Correct", IF(F20>F6, "Perfect", IF(F13>F17, "YES"))) -> YES
C6: 36530 | D6: East | E6: Smartwatch | F6: 10000 | H6: =SUMIF(D3:D24, "South", F3:F24) -> 133300 | I6: =AVERAGEIF(D3:D24, "north", F3:F24) -> 21777.143
C7: 36533 | D7: North | E7: Bass Headphones | F7: 32640 | J7: =IF(F12<>F10, "NO", IF(F6<>F17, "no", IF(F14>F4, "OOOO", IF(F23<>F4, "YES")))) -> FALSE
C8: 36526 | D8: North | E8: Beard trimmer | F8: 4000 | H8: =SUMIF(E3:E24, "Deodarant", F3:F24) -> 16000 | I8: =AVERAGEIF(E3:E24, "wrist watch", F3:F24) -> 48960
C9: 36528 | D9: North | E9: Deodarant | F9: 8000
C10: 36544 | D10: North | E10: Deodarant | F10: 8000 | H10: =SUMIF(E3:E24, "beard trimmer", F3:F24) -> 8000 | I10: =AVERAGEIF(E3:E24, "Earbuds", F3:F24) -> 19350
C11: 36541 | D11: North | E11: Mobile | F11: 42840
C12: 36545 | D12: North | E12: Shaving cream | F12: 8000
C13: 36534 | D13: North | E13: Wrist watch | F13: 48960
C14: 36539 | D14: South | E14: Bass Headphones | F14: 32640
C15: 36538 | D15: South | E15: Earbuds | F15: 35700
C16: 36537 | D16: South | E16: Jackets | F16: 6000
C17: 36546 | D17: South | E17: Smartwatch | F17: 10000
C18: 36540 | D18: South | E18: Wrist watch | F18: 48960
C19: 36536 | D19: West | E19: Beard trimmer | F19: 4000
C20: 36532 | D20: West | E20: Earbuds | F20: 3000
C21: 36527 | D21: West | E21: Hair dryer | F21: 9000
C22: 36543 | D22: West | E22: Hair dryer | F22: 9000
... C24: 36529 | D24: West | E24: Shaving cream | F24: 8000

Sheet IFs Functions
B2: Date | C2: Region | D2: Items | E2: Price | H2: Region | I2: Items | J2: Price
B3: 36531 | C3: East | D3: Footwear | E3: 12000 | H3: South | I3: Smartwatch | J3: >20000
B4: 36542 | C4: East | D4: Mobile | E4: 35700 | H4: North | I4: Beard trimmer | J4: >40000
B5: 36535 | C5: East | D5: Mobile | E5: 42840 | H5: East | I5: Mobile | J5: <=30000
B6: 36536 | C6: East | D6: Mobile | E6: 50000
B7: 36530 | C7: East | D7: Smartwatch | E7: 10000
B8: 36531 | C8: East | D8: Smartwatch | E8: 30000
B9: 36533 | C9: North | D9: Bass Headphones | E9: 30640
B10: 36526 | C10: North | D10: Beard trimmer | E10: 4000 | G10: Sumifs | H10: Averageifs | I10: Minifs | J10: Maxifs
B11: 36528 | C11: North | D11: Deodarant | E11: 8000 | G11: =SUMIFS(E3:E28, C3:C28, "East", D3:D28, "Mobile") -> 128540 | H11: =AVERAGEIFS(E3:E28, C3:C28, "East", D3:D28, "Mobile") -> 42846.667 | I11: =_xlfn.MINIFS(E3:E28, C3:C28, "East", D3:D28, "Mobile") -> 35700 | J11: =_xlfn.MAXIFS(E3:E28, C3:C28, "East", D3:D28, "Mobile") -> 50000
B12: 36544 | C12: North | D12: Deodarant | E12: 10000
B13: 36541 | C13: North | D13: Mobile | E13: 42840 | G13: =SUMIFS(E3:E28, C3:C28, "South", D3:D28, "Bass headphones") -> 74640 | H13: =AVERAGEIFS(E3:E28, C3:C28, "North", D3:D28, "Deodarant") -> 9000 | I13: =_xlfn.MINIFS(E3:E28, C3:C28, "North", D3:D28, "Bass headphones") -> 30640 | J13: =_xlfn.MAXIFS(E3:E28, C3:C28, "West", D3:D28, "hair dryer", E3:E28, ">10000") -> 11000
B14: 36545 | C14: North | D14: Shaving cream | E14: 8000
B15: 36534 | C15: North | D15: Wrist watch | E15: 48960 | G15: =SUMIFS(E3:E28, C3:C28, "West", D3:D28, "Hair dryer", E3:E28, ">5000") -> 27000 | H15: =AVERAGEIFS(E3:E28, C3:C28, "West", D3:D28, "Hair dryer", E3:E28, ">5000") -> 9000 | I15: =_xlfn.MINIFS(E3:E28, C3:C28, "South", D3:D28, "Bass headphones", E3:E28, ">=30000") -> 32640
B16: 36539 | C16: South | D16: Bass Headphones | E16: 32640
B17: 36540 | C17: South | D17: Bass Headphones | E17: 42000
B18: 36538 | C18: South | D18: Earbuds | E18: 35700
B19: 36537 | C19: South | D19: Jackets | E19: 6000
B20: 36546 | C20: South | D20: Smartwatch | E20: 10000
B21: 36540 | C21: South | D21: Wrist watch | E21: 48960
B22: 36536 | C22: West | D22: Beard trimmer | E22: 4000
B23: 36532 | C23: West | D23: Earbuds | E23: 35700
B24: 36527 | C24: West | D24: Hair dryer | E24: 7000
B25: 36543 | C25: West | D25: Hair dryer | E25: 9000
B26: 36544 | C26: West | D26: Hair dryer | E26: 11000
B27: 36547 | C27: West | D27: Mobile | E27: 35700
B28: 36529 | C28: West | D28: Shaving cream | E28: 8000

Sheet Database functions
B1: Date | C1: Region | D1: Items | E1: Price | H1: Region | I1: Items | J1: Price
B2: 36533 | C2: East | D2: Bass Headphones | E2: 2000 | H2: South | I2: Bass Headphones | J2: >20000
B3: 36531 | C3: East | D3: Footwear | E3: 4000
B4: 36542 | C4: East | D4: Mobile | E4: 6000 | H4: Region | I4: Items | J4: Price
B5: 36535 | C5: East | D5: Mobile | E5: 8000 | H5: West | I5: Beard trimmer | J5: >40000
B6: 36530 | C6: East | D6: Smartwatch | E6: 10000
B7: 36531 | C7: East | D7: Smartwatch | E7: 12000 | H7: Items | I7: Region | J7: Price
B8: 36526 | C8: North | D8: Beard trimmer | E8: 14000 | H8: Mobile | I8: East | J8: >3000
B9: 36528 | C9: North | D9: Beard trimmer | E9: 16000
B10: 36530 | C10: North | D10: Beard trimmer | E10: 18000
B11: 36544 | C11: North | D11: Deodarant | E11: 18000
B12: 36545 | C12: North | D12: Shaving cream | E12: 20000 | G12: SUMIFS | H12: DSUM | I12: DAVERAGE | J12: DMIN | K12: DMAX
B13: 36534 | C13: North | D13: Wrist watch | E13: 22000 | G13: =SUMIFS(E2:E28, C2:C28, "South", D2:D28, "Bass headphones", E2:E28, ">20000") -> 70000 | H13: =DSUM(B1:E28, E1, H1:J2) -> 70000 | I13: =DAVERAGE(B1:E28, E1, H1:J2) -> 35000 | J13: =DMIN(B1:E28, E1, H1:J2) -> 30000 | K13: =DMAX(B1:E28, E1, H1:J2) -> 40000
B14: 36535 | C14: North | D14: Wrist watch | E14: 25000
B15: 36539 | C15: South | D15: Bass Headphones | E15: ABC | H15: =DSUM(B1:E28, E1, H4:J5) -> 107000 | I15: =DAVERAGE(B1:E28, E1, H4:J5) -> 53500 | J15: =DMIN(B1:E28, E1, H4:J5) -> 50000 | K15: =DMAX(B1:E28, E1, H4:J5) -> 57000
B16: 36540 | C16: South | D16: Bass Headphones | E16: 30000
B17: 36540 | C17: South | D17: Bass Headphones | E17: 40000 | H17: =DSUM(B1:E29, E1, H7:J8) -> 14000 | I17: =DAVERAGE(B1:E28, E1, H7:J8) -> 7000 | J17: =DMIN(B1:E28, E1, H7:J8) -> 6000 | K17: =DMAX(B1:E28, E1, H7:J8) -> 8000
B18: 36540 | C18: South | D18: Bass Headphones | E18: 15000
B19: 36538 | C19: South | D19: Earbuds | E19: 30000
B20: 36537 | C20: South | D20: Jackets | E20: 32000 | H20: DCOUNT | I20: DCOUNTA | J20: DPRODUCT
B21: 36538 | C21: South | D21: Jackets | E21: 34000 | H21: =DCOUNT(B1:E28, E1,H1:J2) -> 2 | I21: =DCOUNTA(B1:E28, E1, H1:I2) -> 4 | J21: =DPRODUCT(B1:E28, E1, H1:J2) -> 1200000000
B22: 36536 | C22: West | D22: Beard trimmer | E22: 36000
B23: 36537 | C23: West | D23: Beard trimmer | E23: XYZ | H23: =DCOUNT(B1:E28, E1, H4:I5) -> 3 | I23: =DCOUNTA(B1:E28, E1, H4:I5) -> 4 | J23: =DPRODUCT(B1:E28, E1, H4:J5) -> 2850000000
B24: 36537 | C24: West | D24: Beard trimmer | E24: 50000
B25: 36538 | C25: West | D25: Beard trimmer | E25: 57000 | H25: =DCOUNT(B1:E28, E1, H7:I8) -> 2 | I25: =DCOUNTA(B1:E28, E1, H7:I8) -> 2 | J25: =DPRODUCT(B1:E28, E1, H7:J8) -> 48000000
B26: 36532 | C26: West | D26: Earbuds | E26: 38000
B27: 36547 | C27: West | D27: Mobile | E27: 40000
B28: 36529 | C28: West | D28: Shaving cream | E28: 42000
C31: ARRAY
B32: Items | C32: Selling Price (Revenue) | D32: Cost Price (Expenses) | E32: Profit
B33: Jackets | C33: 9000 | D33: 1000
B34: Earbuds | C34: 8000 | D34: 2000
B35: Bass Headphones | C35: 8000 | D35: 4000
B36: Wrist watch | C36: 10000 | D36: 3000
B37: Mobile | C37: 35700 | D37: 10000
B38: Beard trimmer | C38: 15000 | D38: 18000
B39: Jackets | C39: 30000 | D39: 18000
B40: Shaving cream | C40: 32000 | D40: 20000
B41: Smartwatch | C41: 34000 | D41: 22000
B42: Footwear | C42: 36000 | D42: 25000
D43: TOTAL | E43: {=SUM(C33:C42-D33:D42)} -> 94700

Sheet Logical functions
C2: AND, OR, NOT, XOR
B4: Names | C4: GK | D4: Math | E4: English | F4: Science
B5: Harish | C5: 30 | D5: 40 | E5: 49 | F5: 34
B6: Seeta | C6: 82 | D6: 29 | E6: 41 | F6: 56
B7: Aryan | C7: 22 | D7: 64 | E7: 30 | F7: 47 | G7: =IF(OR(C5>50,D5>50,E5>50,F5>50),"PASSED","FAILED") -> FAILED
B8: Sushant | C8: 75 | D8: 21 | E8: 78 | F8: 77 | G8: =IF(OR(C6>50,D6>50,E6>50,F6>50),"PASSED","FAILED") -> PASSED
B9: Mayara | C9: 39 | D9: 37 | E9: 45 | F9: 22 | G9: =IF(OR(C7>50,D7>50,E7>50,F7>50),"PASSED","FAILED") -> PASSED
B10: Neelam | C10: 39 | D10: 71 | E10: 28 | F10: 90 | G10: =IF(AND(C8>50,D8>50,E8>50,F8>50),"PASSED","FAILED") -> FAILED
B11: Uday | C11: 42 | D11: 38 | E11: 12 | F11: 40 | G11: =IF(OR(C9>50,D9>50,E9>50,F9>50),"PASSED","FAILED") -> FAILED
B12: Preetam | C12: 76 | D12: 35 | E12: 35 | F12: 27
B13: Preeti | C13: 39 | D13: 50 | E13: 66 | F13: 26
B14: TOTAL | C14: =SUM(C5:C13) -> 444 | D14: =SUM(D5:D13) -> 385 | E14: =SUM(E5:E13) -> 384 | F14: =SUM(F5:F13) -> 419
B17: OR | C17: TRUE | D17: FALSE | E17: TRUE
B18: AND | C18: TRUE | D18: TRUE | E18: TRUE
B19: AND | C19: FALSE | D19: TRUE | E19: FALSE
B20: XOR | C20: FALSE | D20: TRUE | E20: TRUE
B21: XOR | C21: TRUE | D21: FALSE | E21: TRUE
B22: XOR | C22: TRUE | D22: TRUE | E22: FALSE
A25: Names | B25: Logical Analysis (OR) | C25: Result | D25: Logical Analysis (AND) | E25: Result | F25: Logical Analysis (XOR)
A26: Harish | B26: =OR(C5>50, D5>50, E5>50, F5>50) -> FALSE | C26: =IF(B26=TRUE, "Passed", "Failed") -> Failed | D26: =AND(C5>50, D5>50, E5>50, F5>50) -> FALSE | E26: =IF(D26=TRUE, "Passed", "Failed") -> Failed | F26: =_xlfn.XOR(C5>50, D5>50, E5>50, F5>50) -> FALSE
A27: Seeta | B27: =OR(C6>50, D6>50, E6>50, F6>50) -> TRUE | C27: =IF(B27=TRUE, "Passed", "Failed") -> Passed | D27: =AND(C6>50, D6>50, E6>50, F6>50) -> FALSE | E27: =IF(D27=TRUE, "Passed", "Failed") -> Failed | F27: =_xlfn.XOR(C6>50, D6>50, E6>50, F6>50) -> FALSE
A28: Aryan | B28: =OR(C7>50, D7>50, E7>50, F7>50) -> TRUE | C28: =IF(B28=TRUE, "Passed", "Failed") -> Passed | D28: =AND(C7>50, D7>50, E7>50, F7>50) -> FALSE | E28: =IF(D28=TRUE, "Passed", "Failed") -> Failed | F28: =_xlfn.XOR(C7>50, D7>50, E7>50, F7>50) -> TRUE | G28: XOR result - TRUE, when the number of valid/correct inputs is odd. XOR result - FALSE, when the number of valid/correct inputs is even.
A29: Sushant | B29: =OR(C8>50, D8>50, E8>50, F8>50) -> TRUE | C29: =IF(B29=TRUE, "Passed", "Failed") -> Passed | D29: =AND(C8>50, D8>50, E8>50, F8>50) -> FALSE | E29: =IF(D29=TRUE, "Passed", "Failed") -> Failed | F29: =_xlfn.XOR(C8>50, D8>50, E8>50, F8>50) -> TRUE
A30: Mayara | B30: =OR(C9>50, D9>50, E9>50, F9>50) -> FALSE | C30: =IF(B30=TRUE, "Passed", "Failed") -> Failed | D30: =AND(C9>50, D9>50, E9>50, F9>50) -> FALSE | E30: =IF(D30=TRUE, "Passed", "Failed") -> Failed | F30: =_xlfn.XOR(C9>50, D9>50, E9>50, F9>50) -> FALSE
A31: Neelam | B31: =OR(C10>50, D10>50, E10>50, F10>50) -> TRUE | C31: =IF(B31=TRUE, "Passed", "Failed") -> Passed | D31: =AND(C10>50, D10>50, E10>50, F10>50) -> FALSE | E31: =IF(D31=TRUE, "Passed", "Failed") -> Failed | F31: =_xlfn.XOR(C10>50, D10>50, E10>50, F10>50) -> FALSE
A32: Uday | B32: =OR(C11>50, D11>50, E11>50, F11>50) -> FALSE | C32: =IF(B32=TRUE, "Passed", "Failed") -> Failed | D32: =AND(C11>50, D11>50, E11>50, F11>50) -> FALSE | E32: =IF(D32=TRUE, "Passed", "Failed") -> Failed | F32: =_xlfn.XOR(C11>50, D11>50, E11>50, F11>50) -> FALSE
A33: Preetam | B33: =OR(C12>50, D12>50, E12>50, F12>50) -> TRUE | C33: =IF(B33=TRUE, "Passed", "Failed") -> Passed | D33: =AND(C12>50, D12>50, E12>50, F12>50) -> FALSE | E33: =IF(D33=TRUE, "Passed", "Failed") -> Failed | F33: =_xlfn.XOR(C12>50, D12>50, E12>50, F12>50) -> TRUE
A34: Preeti | B34: =OR(C13>50, D13>50, E13>50, F13>50) -> TRUE | C34: =IF(B34=TRUE, "Passed", "Failed") -> Passed | D34: =AND(C13>50, D13>50, E13>50, F13>50) -> FALSE | E34: =IF(D34=TRUE, "Passed", "Failed") -> Failed | F34: =_xlfn.XOR(C13>50, D13>50, E13>50, F13>50) -> TRUE

Sheet Speak cells, Show hide formulas
C2: Date | D2: Region | E2: Items | F2: Price
C3: 36531 | D3: East | E3: Footwear | F3: 12000 | I3: No
C4: 36542 | D4: East | E4: Mobile | F4: 35700 | I4: Yes
C5: 36535 | D5: East | E5: Mobile | F5: 42840 | I5: Yes, No
C6: 36530 | D6: East | E6: Smartwatch | F6: 10000 | I6: 10, 20
C7: 36533 | D7: North | E7: Bass Headphones | F7: 32640 | I7: YES, NO
C8: 36526 | D8: North | E8: Beard trimmer | F8: 4000 | H8: =IF(F3>F4, "Yes", "No") -> No | I8: Expensive, Inexpensive
C9: 36528 | D9: North | E9: Deodarant | F9: 8000 | H9: =IF(F3<F4, "Yes", "No") -> Yes
C10: 36544 | D10: North | E10: Deodarant | F10: 8000 | H10: =IF(F7>F13, 10, 20) -> 20
C11: 36541 | D11: North | E11: Mobile | F11: 42840 | H11: =IF(F8<F14, 10, 20) -> 10
C12: 36545 | D12: North | E12: Shaving cream | F12: 8000 | H12: =IF(F6=F17, "YES", "NO") -> NO
C13: 36534 | D13: North | E13: Wrist watch | F13: 48960 | H13: =IF(F17=F6, UPPER(I4), UPPER(I3)) -> NO
C14: 36539 | D14: South | E14: Bass Headphones | F14: 32640 | H14: =IF(F20<>F18, "Expensive", "Inexpensive") -> Inexpensive
C15: 36538 | D15: South | E15: Earbuds | F15: 35700 | H15: =IF(F20>F18, "Expensive", "Inexpensive") -> Inexpensive

Sheet Trace precedents and dependents
B2: Month | C2: Product | D2: Sales
B3: January | C3: Pencils | D3: 1000 | F3: 50
B4: February | C4: Books | D4: 5000 | E4: 40 | G4: =SUM(F3,F5,F7,F9,E4) -> 280 | H4: SUM
B5: March | C5: Colors | D5: 1000 | F5: 10
B6: April | C6: Highlighters | D6: 3500 | E6: 70 | G6: =PRODUCT(F5,F3,E6) -> 35000 | H6: PRODUCT
B7: May | C7: Scales/Rulers | D7: 3000 | F7: 80
B8: June | C8: Notebooks | D8: 4000 | E8: 90 | G8: =AVERAGE(F7,F5,F3,E6,E4,E8) -> 56.666667 | H8: AVERAGE
B9: July | C9: Magazines | D9: 4000 | F9: 100
B10: Total | D10: =SUM(D3:D9) -> 21500 | E10: =SUM(E3:E9) -> 200
G11: COUNT | H11: =COUNT(C3:D9) -> 7
G12: COUNTA | H12: =COUNTA(C3:D9) -> 14
C13: =MIN(D3:D9) -> 1000 | D13: MINIMUM | G13: COUNTBLANK | H13: =COUNTBLANK(E3:F9) -> 7
C14: =MAX(D3:D9) -> 5000 | D14: MAXIMUM

Sheet Evaluate formulas
B2: Formula used | C2: Result
B3: 1*2+3*4/2 | C3: =1*2+3*4/2 -> 8
B4: 2*3+3*4/3 | C4: =2*3+3*4/3 -> 10
B5: 3*4-3*4/2 | C5: =3*4-3*4/2 -> 6
B6: 1*(2+3)*4/3 | C6: =1*(2+3)*4/3 -> 6.6666667
B7: 1*2/5+4-3 | C7: =1*2/5+4-3 -> 1.4

Sheet FOrmula auditing 2
B2: Date | C2: Region | D2: Items | E2: Price | G2: Region | H2: Items | I2: Price
B3: 36533 | C3: East | D3: Bass Headphones | E3: 2000 | G3: North | H3: Wrist watch | I3: <30000
B4: 36531 | C4: East | D4: Footwear | E4: 4000
B5: 36542 | C5: East | D5: Mobile | E5: 6000 | G5: Region | H5: Items | I5: Price | K5: =_xlfn.FORMULATEXT(F13) -> =SUMIFS(E3:E27, C3:C27, "north", D3:D27, "Wrist watch")
B6: 36535 | C6: East | D6: Mobile | E6: 8000 | G6: West | H6: Beard trimmer | I6: >40000
B7: 36530 | C7: East | D7: Smartwatch | E7: 10000
B8: 36531 | C8: East | D8: Smartwatch | E8: 10000 | G8: Region | H8: Items | I8: Price
B9: 36526 | C9: North | D9: Beard trimmer | E9: 14000 | G9: East | H9: Mobile | I9: <=30000
B10: 36528 | C10: North | D10: Deodarant | E10: 16000
B11: 36544 | C11: North | D11: Deodarant | E11: 18000
B12: 36545 | C12: North | D12: Shaving cream | E12: 20000 | F12: SUMIFS | G12: DSUM | H12: DAVERAGE | I12: DMIN | J12: DMAX
B13: 36534 | C13: North | D13: Wrist watch | E13: 22000 | F13: =SUMIFS(E3:E27, C3:C27, "north", D3:D27, "Wrist watch") -> 47000 | G13: =DSUM(B2:E27, E2, G2:I3) -> 47000 | H13: =DAVERAGE(B2:E27, E2, G2:I3) -> 23500 | I13: =DMIN(B2:E27, E2, G2:I3) -> 22000 | J13: =DMAX(B2:E27, E2, G2:I3) -> 25000
B14: 36535 | C14: North | D14: Wrist watch | E14: 25000
B15: 36539 | C15: South | D15: Bass Headphones | E15: 10000 | G15: =DSUM(B2:E27, E2, G5:I6) -> 107000 | H15: =DAVERAGE(B2:E27, E2, G5:I6) -> 53500 | I15: =DMIN(B2:E27, E2, G5:I6) -> 50000 | J15: =DMAX(B2:E27, E2, G5:I6) -> 57000
B16: 36540 | C16: South | D16: Bass Headphones | E16: HIGHER
B17: 36540 | C17: South | D17: Bass Headphones | E17: 28000
B18: 36538 | C18: South | D18: Earbuds | E18: 30000 | G18: =DSUM(B2:E27, E2, G8:I9) -> 14000 | H18: =DAVERAGE(B2:E27, E2, G8:I9) -> 7000 | I18: =DMIN(B2:E27, E2, G8:I9) -> 6000 | J18: =DMAX(B2:E27, E2, G8:I9) -> 8000
B19: 36537 | C19: South | D19: Jackets | E19: 32000
B20: 36538 | C20: South | D20: Jackets | E20: 20000
B21: 36536 | C21: West | D21: Beard trimmer | E21: 36000 | G21: DCOUNT | H21: DCOUNTA | I21: DPRODUCT
B22: 36537 | C22: West | D22: Beard trimmer | E22: LOWER
B23: 36537 | C23: West | D23: Beard trimmer | E23: 50000 | G23: =DCOUNT(B2:E27, E2, G2:I3) -> 2 | H23: =DCOUNTA(B2:E27, E2, G2:I3) -> 2 | I23: =DPRODUCT(B2:E27, E2, G2:I3) -> 550000000
B24: 36538 | C24: West | D24: Beard trimmer | E24: 57000
B25: 36532 | C25: West | D25: Earbuds | E25: 38000 | G25: =DCOUNT(B2:E27, E2, G5:I6) -> 2 | H25: =DCOUNTA(B2:E27, E2, G5:I6) -> 2 | I25: =DPRODUCT(B2:E27, E2, G5:I6) -> 2850000000
B26: 36547 | C26: West | D26: Mobile | E26: 40000 | G26: =DCOUNT(B2:E27, E2, G5:H6) -> 3 | H26: =DCOUNTA(B2:E27, E2, G5:H6) -> 4 | I26: =DPRODUCT(B2:E27, E2, G5:H6) -> 102600000000000
B27: 36529 | C27: West | D27: Shaving cream | E27: 42000
G28: =DCOUNT(B2:E27, E2, G8:I9) -> 2 | H28: =DCOUNTA(B2:E27, E2, G8:I9) -> 2 | I28: =DPRODUCT(B2:E27, E2, G8:I9) -> 48000000
E30: =DSUM(#REF!, C19, E19:G20) -> #REF!
C32: =C30 -> 0
G33: =DPRODUCT(#REF!, C12, E12:G13) -> #REF!
F41: =AVERAGE(E3:E27) -> 23391.304
D42: =SUM(E3:E27) -> 538000

Sheet Excel Protection
E5: Formula used | F5: Result
E6: 1*2+3*4/2 | F6: =1*2+3*4/2 -> 8
E7: 2*3+3*4/3 | F7: =2*3+3*4/3 -> 10
E8: 3*4-3*4/2 | F8: =3*4-3*4/2 -> 6
E9: 1*(2+3)*4/3 | F9: =1*(2+3)*4/3 -> 6.6666667
E10: 1*2/5+4-3 | F10: =1*2/5+4-3 -> 1.4

Sheet Text to columns - Delimiter
B3: NAMES | D3: First Name | E3: Last Name | G3: NAMES | I3: First Name | J3: Last Name
B4: Ananya Pandey | D4: Ananya | E4: Pandey | G4: Ananya,,Pandey | I4: Ananya | J4: Pandey
B5: Arohi Sharma | D5: Arohi | E5: Sharma | G5: Arohi,,Sharma | I5: Arohi | J5: Sharma
B6: Mohandas Gandhi | D6: Mohandas | E6: Gandhi | G6: Mohandas,,Gandhi | I6: Mohandas | J6: Gandhi
B7: Mohan Kalra | D7: Mohan | E7: Kalra | G7: Mohan,,Kalra | I7: Mohan | J7: Kalra
B8: Anshu Poonawala | D8: Anshu | E8: Poonawala | G8: Anshu,,Poonawala | I8: Anshu | J8: Poonawala
B9: Rahul Sharma | D9: Rahul | E9: Sharma | G9: Rahul,,Sharma | I9: Rahul | J9: Sharma
B10: Neil Armstrong | D10: Neil | E10: Armstrong | G10: Neil,,Armstrong | I10: Neil | J10: Armstrong
B11: Avnish Agrawal | D11: Avnish | E11: Agrawal | G11: Avnish,,Agrawal | I11: Avnish | J11: Agrawal
B12: Shashank Khan | D12: Shashank | E12: Khan | G12: Shashank,,Khan | I12: Shashank | J12: Khan
B15: NAMES | D15: First Name | E15: Last Name
B16: Ananya,Pandey | D16: Ananya | E16: Pandey | G16: NAMES | H16: S. No. | I16: First Name | J16: Last Name
B17: Arohi,Sharma | D17: Arohi | E17: Sharma | G17: 1. Ananya//Pandey | H17: 1 | I17: Ananya | J17: Pandey
B18: Mohandas,Gandhi | D18: Mohandas | E18: Gandhi | G18: 2. Arohi//Sharma | H18: 2 | I18: Arohi | J18: Sharma
B19: Mohan,Kalra | D19: Mohan | E19: Kalra | G19: 3. Mohandas/Gandhi | H19: 3 | I19: Mohandas | J19: Gandhi
B20: Anshu,Poonawala | D20: Anshu | E20: Poonawala | G20: 4. Mohan//Kalra | H20: 4 | I20: Mohan | J20: Kalra
B21: Rahul,Sharma | D21: Rahul | E21: Sharma | G21: 5. Anshu/Poonawala | H21: 5 | I21: Anshu | J21: Poonawala
B22: Neil,Armstrong | D22: Neil | E22: Armstrong | G22: 6. Rahul//Sharma | H22: 6 | I22: Rahul | J22: Sharma
B23: Avnish,Agrawal | D23: Avnish | E23: Agrawal | G23: 7. Neil/Armstrong | H23: 7 | I23: Neil | J23: Armstrong
B24: Shashank,Khan | D24: Shashank | E24: Khan | G24: 8. Avnish//Agrawal | H24: 8 | I24: Avnish | J24: Agrawal
G25: 9. Shashank/Khan | H25: 9 | I25: Shashank | J25: Khan
B27: NAMES | D27: First Name | E27: Last Name
B28: Ananya;Pandey | D28: Ananya | E28: Pandey
B29: Arohi;Sharma | D29: Arohi | E29: Sharma
B30: Mohandas;Gandhi | D30: Mohandas | E30: Gandhi
B31: Mohan;Kalra | D31: Mohan | E31: Kalra
B32: Anshu;Poonawala | D32: Anshu | E32: Poonawala
B33: Rahul;Sharma | D33: Rahul | E33: Sharma
B34: Neil;Armstrong | D34: Neil | E34: Armstrong
B35: Avnish;Agrawal | D35: Avnish | E35: Agrawal
B36: Shashank;Khan | D36: Shashank | E36: Khan

Sheet Text to columns - Fixed width
B2: Joined | C2: Separate 1 | D2: Separate 2 | H2: Joined | I2: In date format
B3: 2233 | C3: 22 | D3: 33 | H3: 20000815 | I3: 36753
B4: 4455 | C4: 44 | D4: 55 | H4: 20000916 | I4: 36785
B5: 6789 | C5: 67 | D5: 89 | H5: 20001017 | I5: 36816
B6: 2356 | C6: 23 | D6: 56 | H6: 20001118 | I6: 36848
B7: 1227 | C7: 12 | D7: 27 | H7: 20001219 | I7: 36879
B8: 7957 | C8: 79 | D8: 57 | H8: 20001220 | I8: 36880
B9: 1212 | C9: 12 | D9: 12 | H9: 20000721 | I9: 36728
B13: Joined | C13: Separate 1 | D13: Separate 2 | E13: Separate 3 | H13: 15082000 | I13: 36753
B14: 20000815 | C14: 2000 | D14: 08 | E14: 15 | H14: 16092000 | I14: 36785
B15: 20000916 | C15: 2000 | D15: 09 | E15: 16 | H15: 17102000 | I15: 36816
B16: 20001017 | C16: 2000 | D16: 10 | E16: 17 | H16: 18112000 | I16: 36848
B17: 20001118 | C17: 2000 | D17: 11 | E17: 18 | H17: 19122000 | I17: 36879
B18: 20001219 | C18: 2000 | D18: 12 | E18: 19 | H18: 20122000 | I18: 36880
B19: 20001320 | C19: 2000 | D19: 13 | E19: 20 | H19: 21072000 | I19: 36728
B20: 20001421 | C20: 2000 | D20: 14 | E20: 21
B21: 20001522 | C21: 2000 | D21: 15 | E21: 22
B22: 20001623 | C22: 2000 | D22: 16 | E22: 23
B23: 20001724 | C23: 2000 | D23: 17 | E23: 24
B24: 20001825 | C24: 2000 | D24: 18 | E24: 25
B25: 20001926 | C25: 2000 | D25: 19 | E25: 26

Sheet Textsplit function
B1: Randomly arranged words | D1: Items | E1: Prices
B3: Bass Headphones=20000
B4: Earbuds;10000
B5: Shaving Cream;*2000
B6: Jackets:,10000
B7: Beardtrimmer:*&5000
B11: Earbuds=10000, Jackets=4000, beard trimmer=30000
B12: Hairdryer;2000, Shaving cream=1000, Bodylotion*3000, Showergel=2500, Facewash&1000

Sheet Textbefore function
C2: Random text
C4: Bass Headphones=20000 | E4: =_xlfn.TEXTBEFORE(C4, "=") -> #NAME?
C5: Earbuds;10000 | E5: =_xlfn.TEXTBEFORE(C5, ";") -> #NAME?
C6: Shaving Cream;*2000 | E6: =_xlfn.TEXTBEFORE(C6, ";") -> #NAME?
C7: Jackets:,10000 | E7: =_xlfn.TEXTBEFORE(C7, ":") -> #NAME?
C8: Beardtrimmer:*&5000 | E8: =_xlfn.TEXTBEFORE(C8, ":") -> #NAME?
C10: Random text
C11: California = 39648 / 0.03 | D11: =_xlfn.TEXTBEFORE(C11, "=") -> #NAME? | E11: =_xlfn.TEXTBEFORE(C11, " =") -> #NAME? | F11: =_xlfn.TEXTBEFORE(C11, "0.0") -> #NAME? | H11: =LEN(D11) -> #NAME? | I11: =LEN(E11) -> #NAME?
C12: Florida = 22197 / 0.10 | D12: =_xlfn.TEXTBEFORE(C12, "=") -> #NAME? | E12: =_xlfn.TEXTBEFORE(C12, " =") -> #NAME? | F12: =_xlfn.TEXTBEFORE(C12, " ", 3) -> #NAME? | H12: =LEN(D12) -> #NAME? | I12: =LEN(E12) -> #NAME?
C13: New York = 19191 / -0.04 | D13: =_xlfn.TEXTBEFORE(C13, "=") -> #NAME? | E13: =_xlfn.TEXTBEFORE(C13, " =") -> #NAME? | F13: =_xlfn.TEXTBEFORE(C13, " ", 3) -> #NAME? | H13: =LEN(D13) -> #NAME? | I13: =LEN(E13) -> #NAME?
C14: Illinois = 12518 / -0.04 | D14: =_xlfn.TEXTBEFORE(C14, "=") -> #NAME? | E14: =_xlfn.TEXTBEFORE(C14, " =") -> #NAME? | F14: =_xlfn.TEXTBEFORE(C14, " ", 3) -> #NAME? | H14: =LEN(D14) -> #NAME? | I14: =LEN(E14) -> #NAME?
C15: Georgia = 36299 / 0.09 | D15: =_xlfn.TEXTBEFORE(C15, "=") -> #NAME? | E15: =_xlfn.TEXTBEFORE(C15, " =") -> #NAME? | F15: =_xlfn.TEXTBEFORE(C15, " ", 3) -> #NAME? | H15: =LEN(D15) -> #NAME? | I15: =LEN(E15) -> #NAME?
C16: Virginia = 86321 / 0.5 | D16: =_xlfn.TEXTBEFORE(C16, "=") -> #NAME? | E16: =_xlfn.TEXTBEFORE(C16, " =") -> #NAME? | F16: =_xlfn.TEXTBEFORE(C16, " ", 3) -> #NAME? | H16: =LEN(D16) -> #NAME? | I16: =LEN(E16) -> #NAME?
C17: Oklahoma = 40017 / 0.24 | D17: =_xlfn.TEXTBEFORE(C17, "=") -> #NAME? | E17: =_xlfn.TEXTBEFORE(C17, " =") -> #NAME? | F17: =_xlfn.TEXTBEFORE(C17, " ", 3) -> #NAME? | H17: =LEN(D17) -> #NAME? | I17: =LEN(E17) -> #NAME?
C18: West Virginia = 17571 / -0.78 | D18: =_xlfn.TEXTBEFORE(C18, "=") -> #NAME? | E18: =_xlfn.TEXTBEFORE(C18, " =") -> #NAME? | F18: =_xlfn.TEXTBEFORE(C18, " ", 3) -> #NAME? | H18: =LEN(D18) -> #NAME? | I18: =LEN(E18) -> #NAME?
C19: Hawaii = 14009 / -0.1 | D19: =_xlfn.TEXTBEFORE(C19, "=") -> #NAME? | E19: =_xlfn.TEXTBEFORE(C19, " =") -> #NAME? | F19: =_xlfn.TEXTBEFORE(C19, " ", 3) -> #NAME? | H19: =LEN(D19) -> #NAME? | I19: =LEN(E19) -> #NAME?
C20: New Hampshire = 13789 / 0.5 | D20: =_xlfn.TEXTBEFORE(C20, "=") -> #NAME? | E20: =_xlfn.TEXTBEFORE(C20, " =") -> #NAME? | F20: =_xlfn.TEXTBEFORE(C20, " ", 3) -> #NAME? | H20: =LEN(D20) -> #NAME? | I20: =LEN(E20) -> #NAME?
C21: Maine = 15967 / 0.08 | D21: =_xlfn.TEXTBEFORE(C21, "=") -> #NAME? | E21: =_xlfn.TEXTBEFORE(C21, " =") -> #NAME? | F21: =_xlfn.TEXTBEFORE(C21, " ", 3) -> #NAME? | H21: =LEN(D21) -> #NAME? | I21: =LEN(E21) -> #NAME?
C22: Montana = 10311 / 0.75 | D22: =_xlfn.TEXTBEFORE(C22, "=") -> #NAME? | E22: =_xlfn.TEXTBEFORE(C22, " =") -> #NAME? | F22: =_xlfn.TEXTBEFORE(C22, " ", 3) -> #NAME? | H22: =LEN(D22) -> #NAME? | I22: =LEN(E22) -> #NAME?
C23: Rhode Island = 10658 / 0.1 | D23: =_xlfn.TEXTBEFORE(C23, "=") -> #NAME? | E23: =_xlfn.TEXTBEFORE(C23, " =") -> #NAME? | F23: =_xlfn.TEXTBEFORE(C23, " ", 3) -> #NAME? | H23: =LEN(D23) -> #NAME? | I23: =LEN(E23) -> #NAME?
C25: Random text
C26: California = 39648 = / 0.03 | D26: =_xlfn.TEXTBEFORE(C26, " =") -> #NAME? | E26: =_xlfn.TEXTBEFORE(C26, " =", 2) -> #NAME? | F26: =_xlfn.TEXTBEFORE(C26, " =", 2) -> #NAME?
C27: Florida = 22197 = / 0.10 | D27: =_xlfn.TEXTBEFORE(C27, " =") -> #NAME? | E27: =_xlfn.TEXTBEFORE(C27, " =", 2) -> #NAME? | F27: =_xlfn.TEXTBEFORE(C27, " =", 20) -> #NAME?
C28: New York = 19191 = / -0.04 | D28: =_xlfn.TEXTBEFORE(C28, " =") -> #NAME? | E28: =_xlfn.TEXTBEFORE(C28, " =", 2) -> #NAME? | F28: =_xlfn.TEXTBEFORE(C28, " =", 3) -> #NAME?
C29: Illinois = 12518 = / -0.04 | D29: =_xlfn.TEXTBEFORE(C29, " =") -> #NAME? | E29: =_xlfn.TEXTBEFORE(C29, " =", 2) -> #NAME? | F29: =_xlfn.TEXTBEFORE(C29, " =", 2) -> #NAME?
C30: Georgia = 36299 = / 0.09 | D30: =_xlfn.TEXTBEFORE(C30, " =") -> #NAME? | E30: =_xlfn.TEXTBEFORE(C30, " =", 2) -> #NAME? | F30: =_xlfn.TEXTBEFORE(C30, " =", 2) -> #NAME?
C31: Virginia = 86321 = / 0.5 | D31: =_xlfn.TEXTBEFORE(C31, " =") -> #NAME? | E31: =_xlfn.TEXTBEFORE(C31, " =", 2) -> #NAME? | F31: =_xlfn.TEXTBEFORE(C31, " =", 2) -> #NAME?
C32: Oklahoma = 40017 / = 0.24 | D32: =_xlfn.TEXTBEFORE(C32, " =") -> #NAME? | E32: =_xlfn.TEXTBEFORE(C32, " =", 2) -> #NAME? | F32: =_xlfn.TEXTBEFORE(C32, " =", 2) -> #NAME?
C33: West Virginia = 17571 = / -0.78 | D33: =_xlfn.TEXTBEFORE(C33, " =") -> #NAME? | E33: =_xlfn.TEXTBEFORE(C33, " =", 2) -> #NAME? | F33: =_xlfn.TEXTBEFORE(C33, " =", 2) -> #NAME?
C34: Hawaii = 14009 / = -0.1 | D34: =_xlfn.TEXTBEFORE(C34, " =") -> #NAME? | E34: =_xlfn.TEXTBEFORE(C34, " =", 2) -> #NAME? | F34: =_xlfn.TEXTBEFORE(C34, " =", 2) -> #NAME?
C35: New Hampshire = 13789 = / 0.5 | D35: =_xlfn.TEXTBEFORE(C35, " =") -> #NAME? | E35: =_xlfn.TEXTBEFORE(C35, " =", 2) -> #NAME? | F35: =_xlfn.TEXTBEFORE(C35, " =", 2) -> #NAME?
C36: Maine = 15967 / = 0.08 | D36: =_xlfn.TEXTBEFORE(C36, " =") -> #NAME? | E36: =_xlfn.TEXTBEFORE(C36, " =", 2) -> #NAME? | F36: =_xlfn.TEXTBEFORE(C36, " =", 2) -> #NAME?
C37: Montana = 10311 = / 0.75 | D37: =_xlfn.TEXTBEFORE(C37, " =") -> #NAME? | E37: =_xlfn.TEXTBEFORE(C37, " =", 2) -> #NAME? | F37: =_xlfn.TEXTBEFORE(C37, " =", 2) -> #NAME?
C38: Rhode Island = 10658 / = 0.1 | D38: =_xlfn.TEXTBEFORE(C38, " =") -> #NAME? | E38: =_xlfn.TEXTBEFORE(C38, " =", 2) -> #NAME? | F38: =_xlfn.TEXTBEFORE(C38, " =", 2) -> #NAME?

Sheet Textafter function
C2: Random text
C4: Bass Headphones=20000 | E4: =_xlfn.TEXTAFTER(C4, "=") -> #NAME?
C5: Earbuds;10000 | E5: =_xlfn.TEXTAFTER(C5, ";") -> #NAME?
C6: Shaving Cream;*2000 | E6: =_xlfn.TEXTAFTER(C6, "*") -> #NAME?
C7: Jackets:,10000 | E7: =_xlfn.TEXTAFTER(C7, ",") -> #NAME?
C8: Beardtrimmer:*&5000 | E8: =_xlfn.TEXTAFTER(C8, "&") -> #NAME?
C10: Random text | E10: Number | F10: Growth rate | H10: =_xlfn.TEXTAFTER(C4, "headphones", 1, 1, ,) -> #NAME?
C11: California = 39648 / 0.03 | E11: =_xlfn.TEXTBEFORE(_xlfn.TEXTAFTER(C11, "= "), " /") -> #NAME? | F11: =_xlfn.TEXTAFTER(C11, "/ ") -> #NAME?
C12: Florida = 22197 / 0.10 | E12: =_xlfn.TEXTBEFORE(_xlfn.TEXTAFTER(C12, "= "), " /") -> #NAME? | F12: =_xlfn.TEXTAFTER(C12, "/ ") -> #NAME? | H12: =_xlfn.TEXTAFTER(C4, "headphones", 1, 0, , "Not present") -> #NAME?
C13: New York = 19191 / -0.04 | E13: =_xlfn.TEXTBEFORE(_xlfn.TEXTAFTER(C13, "= "), " /") -> #NAME? | F13: =_xlfn.TEXTAFTER(C13, "/ ") -> #NAME?
C14: Illinois = 12518 / -0.04 | E14: =_xlfn.TEXTBEFORE(_xlfn.TEXTAFTER(C14, "= "), " /") -> #NAME? | F14: =_xlfn.TEXTAFTER(C14, "/ ") -> #NAME?
C15: Georgia = 36299 / 0.09 | E15: =_xlfn.TEXTBEFORE(_xlfn.TEXTAFTER(C15, "= "), " /") -> #NAME? | F15: =_xlfn.TEXTAFTER(C15, "/ ") -> #NAME? | H15: =_xlfn.TEXTAFTER(C11, ";", 1, , , "Its not there") -> #NAME?
C16: Virginia = 86321 / 0.5 | E16: =_xlfn.TEXTBEFORE(_xlfn.TEXTAFTER(C16, "= "), " /") -> #NAME? | F16: =_xlfn.TEXTAFTER(C16, "/ ") -> #NAME? | H16: =_xlfn.TEXTAFTER(C11, ";", 1, , ,) -> #NAME?
C17: Oklahoma = 40017 / 0.24 | E17: =_xlfn.TEXTBEFORE(_xlfn.TEXTAFTER(C17, "= "), " /") -> #NAME? | F17: =_xlfn.TEXTAFTER(C17, "/ ") -> #NAME?
C19: West Virginia = 17571 / -0.78 | E19: =_xlfn.TEXTAFTER(_xlfn.TEXTBEFORE(C19, " /"), "= ") -> #NAME? | F19: =_xlfn.TEXTAFTER(C19, "/ ") -> #NAME?
C20: Hawaii = 14009 / -0.1 | E20: =_xlfn.TEXTAFTER(_xlfn.TEXTBEFORE(C20, " /"), "= ") -> #NAME? | F20: =_xlfn.TEXTAFTER(C20, "/ ") -> #NAME?
C21: New Hampshire = 13789 / 0.5 | E21: =_xlfn.TEXTAFTER(_xlfn.TEXTBEFORE(C21, " /"), "= ") -> #NAME? | F21: =_xlfn.TEXTAFTER(C21, "/ ") -> #NAME?
C22: Maine = 15967 / 0.08 | E22: =_xlfn.TEXTAFTER(_xlfn.TEXTBEFORE(C22, " /"), "= ") -> #NAME? | F22: =_xlfn.TEXTAFTER(C22, "/ ") -> #NAME?
C23: Montana = 10311 / 0.75 | E23: =_xlfn.TEXTAFTER(_xlfn.TEXTBEFORE(C23, " /"), "= ") -> #NAME? | F23: =_xlfn.TEXTAFTER(C23, "/ ") -> #NAME?
C24: Rhode Island = 10658 / 0.1 | E24: =_xlfn.TEXTAFTER(_xlfn.TEXTBEFORE(C24, " /"), "= ") -> #NAME? | F24: =_xlfn.TEXTAFTER(C24, "/ ") -> #NAME?

Sheet Naming ranges
G3: Numbers
G4: 455
G5: 2432
C6: Month | D6: Product | E6: Sales | G6: 6868
C7: January | D7: Pencils | E7: 1000 | G7: 6876
C8: February | D8: Pens | E8: 5000 | G8: 35353
C9: March | D9: Colors | E9: 1000 | G9: 242434
C10: April | D10: Highlighters | E10: 3500 | G10: 344323
C11: May | D11: Scales/Rulers | E11: 3000 | G11: 344343
C12: June | D12: Novels | E12: 4000 | G12: 575343
C13: July | D13: Magazines | E13: 4000 | G13: 55645645
C14: Total | E14: =SUM(E7:E13) -> 21500 | G14: 67786786
E16: =SUM(Sales) -> #REF!
I17: {=Sales*10} -> #REF!
D18: =SUM(Sales) -> #REF!

Sheet Tables in Excel
D2: S.No. | E2: Months | F2: Items | G2: Cost Price | H2: Selling Price
D3: 1 | E3: January | F3: Pencils | G3: 1000 | H3: 1
D4: 2 | E4: February | F4: Pens | G4: 5000 | H4: 2
D5: 3 | E5: March | F5: Colors | G5: 1000 | H5: 3
D6: 4 | E6: April | F6: Highlighters | G6: 3500 | H6: 4
D7: 5 | E7: May | F7: Scales/Rulers | G7: 3000 | H7: 5
D8: 6 | E8: June | F8: Novels | G8: 4000 | H8: 6
D9: 7 | E9: July | F9: Magazines | G9: 4000 | H9: 7
D10: 8 | E10: January | F10: Pencils | G10: 1000 | H10: 8
D11: 9 | E11: February | F11: Pens | G11: 5000 | H11: 9
D12: 10 | E12: March | F12: Colors | G12: 1000
D13: 11 | E13: April | F13: Highlighters | G13: 3500
D14: 12 | E14: May | F14: Scales/Rulers | G14: 3000
D15: 13 | E15: June | F15: Novels | G15: 4000
D16: 14 | E16: July | F16: Magazines | G16: 4000
D17: 15 | E17: January | F17: Pencils | G17: 1000
D18: 16 | E18: February | F18: Pens | G18: 5000
D19: 17 | E19: March | F19: Colors | G19: 1000
D20: 18 | E20: April | F20: Highlighters | G20: 3500
D21: 19 | E21: May | F21: Scales/Rulers | G21: 3000
D22: 20 | E22: June | F22: Novels | G22: 4000
D23: 21 | E23: July | F23: Magazines | G23: 4000
... D37: 35 | E37: July | F37: Magazines | G37: 4000
D38: Total | G38: =SUBTOTAL(109,Table8[Cost Price]) -> 107500

Sheet Data Validation
B4: Whole number | C4: 400 | D4: 200 | E4: 100 | F4: 400
B5: Text length | C5: Mumbai | D5: Delhi | E5: Jhansi | F5: Lucknow | G5: Jamshedpur
B6: Date | C6: 44997 | D6: 45392 | E6: 45976 | F6: 44927
B7: Date 2 | C7: 44145 | D7: 36255 | E7: 41030
B8: Time | C8: 0.5 | D8: 0.625 | E8: 0.875 | F8: 0.41666667 | G8: 0.35416667
B9: Time 2 | C9: 0.25 | D9: 0.79166667 | E9: 0.58333333 | F9: 0.70833333

Sheet Dropdown
C3: Student's Name | D3: Student's age (in years) | E3: Student's grade | F3: Did the student pass?
C4: Rajnish Gupta | D4: 13 | E4: 4 | F4: NO
C5: Sushant Singh | D5: 19 | E5: 9 | F5: YES
C6: Kritika Sharma | D6: 18 | E6: 5 | F6: NOT SURE
C7: Sasha | D7: 12 | E7: 7 | F7: NOT SURE

Sheet Data for dropdown
B2: Names
B3: Adarsh Singh | F3: Grades
B4: Kritika Sharma | F4: 5
B5: Rajiv Dixit | D5: Ages | F5: 6
B6: Rajnish Gupta | D6: 15 | F6: 10
B7: Kritika Kumari | D7: 12 | F7: 4
B8: Sushant Singh | D8: 19 | F8: 9
B9: Sasha | D9: 13 | F9: 8
D10: 18 | F10: 7
D11: 20

Sheet Dependent dropdown
F2: Data Types | G2: Alphabets | H2: Numbers | I2: Symbols
F3: Subcategories | G3: A | H3: 10 | I3: @
G4: B | H4: 20 | I4: #
G5: C | H5: 30 | I5: %
B6: Data Types | C6: Subcategories | G6: D | H6: 40 | I6: *
B7: Numbers | G7: E | H7: 50 | I7: !
B8: Symbols | C8: ; | G8: F | H8: 60 | I8: ?
B9: Alphabets | C9: D | G9: G | H9: 70 | I9: ;
B10: Numbers | C10: 30 | G10: H | H10: 80 | I10: :
B11: Alphabets | C11: B
E14: Data Types | F14: Subcategories | G14: with named ranges
E15: Symbols | F15: #
E16: Numbers | F16: 30
E17: Alphabets | F17: C

Sheet Index and Match functions
B2: Date | C2: Region | D2: Items | E2: Price | G2: Lookup values | H2: Footwear | I2: Shaving cream | J2: Earbuds | K2: Wrist watch | L2: Mobile
B3: 36533 | C3: East | D3: Bass Headphones | E3: 2000
B4: 36531 | C4: East | D4: Footwear | E4: 4000 | G4: Positions from Match function | H4: =MATCH(H2, D3:D16) -> 2 | I4: =MATCH(I2, D3:D16, 0) -> 7 | J4: =MATCH(J2, D3:D16, 0) -> 10 | K4: =MATCH(K2, D3:D16, 0) -> 8 | L4: =MATCH(L2, D3:D16, 0) -> 3
B5: 36542 | C5: East | D5: Mobile | E5: 6000
B6: 36531 | C6: East | D6: Smartwatch | E6: 10000
B7: 36526 | C7: North | D7: Beard trimmer | E7: 14000 | G7: Column numbers | H7: 2 | I7: 4 | J7: 1
B8: 36528 | C8: North | D8: Deodarant | E8: 16000 | G8: Row numbers | H8: 3 | I8: 9 | J8: 6
B9: 36545 | C9: North | D9: Shaving cream | E9: 20000
B10: 36535 | C10: North | D10: Wrist watch | E10: 25000 | G10: Values from Index function - 1D | H10: {=INDEX(D3:D16, H8)} -> Mobile | I10: {=INDEX(C3:C16, I8)} -> South | J10: {=INDEX(E3:E16, J8)} -> 16000
B11: 36540 | C11: South | D11: Bass Headphones | E11: 28000 | G11: Values from Index function - 2D | H11: {=INDEX(B3:E16, H8, H7)} -> East | I11: {=INDEX(B3:E16, I8, I7)} -> 28000 | J11: {=INDEX(B3:E16, J8, J7)} -> 36528
B12: 36538 | C12: South | D12: Earbuds | E12: 30000
B13: 36538 | C13: South | D13: Jackets | E13: 20000
B14: 36536 | C14: West | D14: Beard trimmer | E14: 36000
B15: 36532 | C15: West | D15: Earbuds | E15: 38000
B16: 36547 | C16: West | D16: Mobile | E16: 40000

Sheet HLOOKUP
B4: Region | C4: East | D4: East | E4: East | F4: East | G4: East | H4: North | I4: North | J4: North | K4: North | L4: North
B5: Items | C5: Bass Headphones | D5: Footwear | E5: Mobile | F5: Mobile | G5: Smartwatch | H5: Beard trimmer | I5: Deodarant | J5: Deodarant | K5: Shaving cream | L5: Wrist watch
B6: Price | C6: 2000 | D6: 4000 | E6: 6000 | F6: 8000 | G6: 10000 | H6: 14000 | I6: 16000 | J6: 18000 | K6: 20000 | L6: 25000
B7: Date | C7: 36533 | D7: 36531 | E7: 36542 | F7: 36535 | G7: 36531 | H7: 36526 | I7: 36528 | J7: 36544 | K7: 36545 | L7: 36535
B10: Lookup values | C10: Price | D10: Date
B11: Footwear | C11: =HLOOKUP(B11,$B$5:$L$6,2,FALSE) -> 4000 | D11: =HLOOKUP(B11,$B$5:$L$7,3,FALSE) -> 36531
B12: Smartwatch | C12: =HLOOKUP(B12,$B$5:$L$6,2,FALSE) -> 10000 | D12: =HLOOKUP(B12,$B$5:$L$7,3,FALSE) -> 36531
B13: Deodarant | C13: =HLOOKUP(B13,$B$5:$L$6,2,FALSE) -> 16000 | D13: =HLOOKUP(B13,$B$5:$L$7,3,FALSE) -> 36528
B14: Beard trimmer | C14: =HLOOKUP(B14,$B$5:$L$6,2,FALSE) -> 14000 | D14: =HLOOKUP(B14,$B$5:$L$7,3,FALSE) -> 36526
B15: Shaving cream | C15: =HLOOKUP(B15,$B$5:$L$6,2,FALSE) -> 20000 | D15: =HLOOKUP(B15,$B$5:$L$7,3,FALSE) -> 36545
B16: Wrist watch | C16: =HLOOKUP(B16,$B$5:$L$6,2,FALSE) -> 25000 | D16: =HLOOKUP(B16,$B$5:$L$7,3,FALSE) -> 36535
B17: Mobile | C17: =HLOOKUP(B17,$B$5:$L$6,2,FALSE) -> 6000 | D17: =HLOOKUP(B17,$B$5:$L$7,3,FALSE) -> 36542
B18: Bass Headphones | C18: =HLOOKUP(B18,$B$5:$L$6,2,FALSE) -> 2000 | D18: =HLOOKUP(B18,$B$5:$L$7,3,FALSE) -> 36533
B19: Footwear | C19: =HLOOKUP(B19,$B$5:$L$6,2,FALSE) -> 4000 | D19: =HLOOKUP(B19,$B$5:$L$7,3,FALSE) -> 36531

Sheet VLOOKUP
B2: Items | C2: Price | D2: Date | E2: Region
B3: Bass Headphones | C3: 2000 | D3: 36533 | E3: East | G3: Lookup values | H3: Footwear | I3: Smartwatch | J3: Deodarant | K3: Beard trimmer | L3: Shaving cream | M3: Wrist watch | N3: Mobile | O3: Bass Headphones
B4: Footwear | C4: 4000 | D4: 36531 | E4: East | G4: Price | H4: =VLOOKUP(H3,$B$2:$C$20,2,FALSE) -> 4000 | I4: =VLOOKUP(I3,$B$2:$C$20,2,FALSE) -> 10000 | J4: =VLOOKUP(J3,$B$2:$C$20,2,FALSE) -> 16000 | K4: =VLOOKUP(K3,$B$2:$C$20,2,FALSE) -> 14000 | L4: =VLOOKUP(L3,$B$2:$C$20,2,FALSE) -> 20000 | M4: =VLOOKUP(M3,$B$2:$C$20,2,FALSE) -> 25000 | N4: =VLOOKUP(N3,$B$2:$C$20,2,FALSE) -> 6000 | O4: =VLOOKUP(O3,$B$2:$C$20,2,FALSE) -> 2000
B5: Mobile | C5: 6000 | D5: 36542 | E5: East | G5: Date | H5: =VLOOKUP(H3,$B$2:$D$20,3,FALSE) -> 36531 | I5: =VLOOKUP(I3,$B$2:$D$20,3,FALSE) -> 36531 | J5: =VLOOKUP(J3,$B$2:$D$20,3,FALSE) -> 36528 | K5: =VLOOKUP(K3,$B$2:$D$20,3,FALSE) -> 36526 | L5: =VLOOKUP(L3,$B$2:$D$20,3,FALSE) -> 36545 | M5: =VLOOKUP(M3,$B$2:$D$20,3,FALSE) -> 36535 | N5: =VLOOKUP(N3,$B$2:$D$20,3,FALSE) -> 36542 | O5: =VLOOKUP(O3,$B$2:$D$20,3,FALSE) -> 36533
B6: Mobile | C6: 8000 | D6: 36535 | E6: East | G6: Region | H6: =VLOOKUP(H3,$B$2:$E$20,4,FALSE) -> East | I6: =VLOOKUP(I3,$B$2:$E$20,4,FALSE) -> East | J6: =VLOOKUP(J3,$B$2:$E$20,4,FALSE) -> North | K6: =VLOOKUP(K3,$B$2:$E$20,4,FALSE) -> North | L6: =VLOOKUP(L3,$B$2:$E$20,4,FALSE) -> North | M6: =VLOOKUP(M3,$B$2:$E$20,4,FALSE) -> North | N6: =VLOOKUP(N3,$B$2:$E$20,4,FALSE) -> East | O6: =VLOOKUP(O3,$B$2:$E$20,4,FALSE) -> East
B7: Smartwatch | C7: 10000 | D7: 36531 | E7: East
B8: Beard trimmer | C8: 14000 | D8: 36526 | E8: North
B9: Deodarant | C9: 16000 | D9: 36528 | E9: North
B10: Deodarant | C10: 18000 | D10: 36544 | E10: North
B11: Shaving cream | C11: 20000 | D11: 36545 | E11: North
B12: Wrist watch | C12: 25000 | D12: 36535 | E12: North
B13: Bass Headphones | C13: 28000 | D13: 36540 | E13: South
B14: Earbuds | C14: 30000 | D14: 36538 | E14: South
B15: Jackets | C15: 20000 | D15: 36538 | E15: South
B16: Beard trimmer | C16: 36000 | D16: 36536 | E16: West
B17: Beard trimmer | C17: 50000 | D17: 36537 | E17: West
B18: Earbuds | C18: 38000 | D18: 36532 | E18: West
... B20: Shaving cream | C20: 42000 | D20: 36529 | E20: West

Sheet LOOKUP
B3: Items | C3: Price
B4: Bass Headphones | C4: 2000 | F4: Lookup values | G4: Price
B5: Beard trimmer | C5: 14000 | F5: Shaving cream | G5: =LOOKUP(F5, B4:C13) -> 20000
B6: Deodarant | C6: 16000 | F6: Footwear | G6: =LOOKUP(F6, B4:C13) -> 4000
B7: Earbuds | C7: 30000 | F7: Beard trimmer | G7: =LOOKUP(F7, B4:C13) -> 14000
B8: Footwear | C8: 4000 | F8: Jackets | G8: =LOOKUP(F8, B4:C13) -> 20000
B9: Jackets | C9: 20000
B10: Mobile | C10: 16000
B11: Shaving cream | C11: 20000
B12: Smartwatch | C12: 10000
B13: Wrist watch | C13: 25000
B16: Items | C16: Date | D16: Region | E16: Price | G16: Lookup values | H16: Price | I16: Region | J16: Date
B17: Bass Headphones | C17: 36528 | D17: North | E17: 16000 | G17: Shaving cream | H17: =LOOKUP(G17, $B$17:$B$34, $E$17:$E$34) -> 10000 | I17: =LOOKUP(G17, $B$17:$B$34, $D$17:$D$34) -> East | J17: =LOOKUP(G17, $B$17:$C$34) -> 36531
B18: Bass Headphones | C18: 36526 | D18: North | E18: 14000 | G18: Footwear | H18: =LOOKUP(G18, $B$17:$B$34, $E$17:$E$34) -> 20000 | I18: =LOOKUP(G18, $B$17:$B$34, $D$17:$D$34) -> South | J18: =LOOKUP(G18, $B$17:$C$34) -> 36538
B19: Beard trimmer | C19: 36533 | D19: East | E19: 2000 | G19: Beard trimmer | H19: =LOOKUP(G19, $B$17:$B$34, $E$17:$E$34) -> 4000 | I19: =LOOKUP(G19, $B$17:$B$34, $D$17:$D$34) -> East | J19: =LOOKUP(G19, $B$17:$C$34) -> 36531
B20: Beard trimmer | C20: 36537 | D20: West | E20: 50000 | G20: Jackets | H20: =LOOKUP(G20, $B$17:$B$34, $E$17:$E$34) -> 42000 | I20: =LOOKUP(G20, $B$17:$B$34, $D$17:$D$34) -> West | J20: =LOOKUP(G20, $B$17:$C$34) -> 36529
B21: Beard trimmer | C21: 36531 | D21: East | E21: 4000 | G21: Bass headphones | H21: =LOOKUP(G21, $B$17:$B$34, $E$17:$E$34) -> 14000 | I21: =LOOKUP(G21, $B$17:$B$34, $D$17:$D$34) -> North | J21: =LOOKUP(G21, $B$17:$C$34) -> 36526
B22: Deodarant | C22: 36544 | D22: North | E22: 18000 | G22: Smartwatch | H22: =LOOKUP(G22, $B$17:$B$34, $E$17:$E$34) -> 25000 | I22: =LOOKUP(G22, $B$17:$B$34, $D$17:$D$34) -> North | J22: =LOOKUP(G22, $B$17:$C$34) -> 36535
B23: Deodarant | C23: 36538 | D23: South | E23: 30000 | G23: Earbuds | H23: =LOOKUP(G23, $B$17:$B$34, $E$17:$E$34) -> 6000 | I23: =LOOKUP(G23, $B$17:$B$34, $D$17:$D$34) -> East | J23: =LOOKUP(G23, $B$17:$C$34) -> 36542
B24: Earbuds | C24: 36532 | D24: West | E24: 38000
B25: Earbuds | C25: 36542 | D25: East | E25: 6000
B26: Footwear | C26: 36538 | D26: South | E26: 20000
B27: Jackets | C27: 36529 | D27: West | E27: 42000
B28: Mobile | C28: 36535 | D28: East | E28: 8000
B29: Mobile | C29: 36547 | D29: West | E29: 40000
B30: Mobile | C30: 36545 | D30: North | E30: 20000
B31: Shaving cream | C31: 36540 | D31: South | E31: 28000
B32: Shaving cream | C32: 36531 | D32: East | E32: 10000
B33: Smartwatch | C33: 36535 | D33: North | E33: 25000
B34: Wrist watch | C34: 36536 | D34: West | E34: 36000

Sheet XLOOKUP
B2: Date | C2: Region | D2: Items | E2: Price
B3: 36533 | C3: East | D3: Bass Headphones | E3: 2000
B4: 36540 | C4: South | D4: Bass Headphones | E4: 28000 | G4: Lookup values | H4: Region | I4: Price | J4: Price
B5: 36526 | C5: North | D5: Beard trimmer | E5: 14000 | G5: Bass Headphones | H5: =_xlfn.XLOOKUP(G5,$D$3:$D$18,$C$3:$C$18,) -> East | I5: =_xlfn.XLOOKUP(G5,D3:D18,E3:E18) -> 2000 | J5: =_xlfn.XLOOKUP(G5,$D$3:$D$18,$E$3:$E$18,,,-1) -> 28000
B6: 36536 | C6: West | D6: Beard trimmer | E6: 36000 | G6: Bass Headphones | H6: =_xlfn.XLOOKUP(G6,D3:D18,C3:C18, ,,-1) -> South | I6: =_xlfn.XLOOKUP(G6,$D$4:$D$19,$E$4:$E$19) -> 28000 | J6: =_xlfn.XLOOKUP(G6,$D$3:$D$18,$E$3:$E$18,,,-1) -> 28000
B7: 36528 | C7: North | D7: Deodarant | E7: 16000 | G7: Earbuds | H7: =_xlfn.XLOOKUP(G7,$D$3:$D$18,$C$3:$C$18,) -> South | I7: =_xlfn.XLOOKUP(G7,$D$4:$D$19,$E$4:$E$19) -> 30000 | J7: =_xlfn.XLOOKUP(G7,$D$3:$D$18,$E$3:$E$18,,,-1) -> 38000
B8: 36544 | C8: North | D8: Deodarant | E8: 18000 | G8: Jackets | H8: =_xlfn.XLOOKUP(G8,$D$3:$D$18,$C$3:$C$18,) -> South | I8: =_xlfn.XLOOKUP(G8,$D$4:$D$19,$E$4:$E$19) -> 20000 | J8: =_xlfn.XLOOKUP(G8,$D$3:$D$18,$E$3:$E$18,,,-1) -> 20000
B9: 36538 | C9: South | D9: Earbuds | E9: 30000 | G9: Smartwatch | H9: =_xlfn.XLOOKUP(G9,$D$3:$D$18,$C$3:$C$18,) -> East | I9: =_xlfn.XLOOKUP(G9,$D$4:$D$19,$E$4:$E$19) -> 10000 | J9: =_xlfn.XLOOKUP(G9,$D$3:$D$18,$E$3:$E$18,,,-1) -> 10000
B10: 36532 | C10: West | D10: Earbuds | E10: 38000
B11: 36531 | C11: East | D11: Footwear | E11: 4000
B12: 36538 | C12: South | D12: Jackets | E12: 20000
B13: 36542 | C13: East | D13: Mobile | E13: 6000
B14: 36535 | C14: East | D14: Mobile | E14: 8000
B15: 36545 | C15: North | D15: Shaving cream | E15: 20000
B16: 36529 | C16: West | D16: Shaving cream | E16: 42000
B17: 36531 | C17: East | D17: Smartwatch | E17: 10000
B18: 36535 | C18: North | D18: Wrist watch | E18: 25000
A21: Items | B21: Bass Headphones | C21: Bass Headphones | D21: Beard trimmer | E21: Beard trimmer | F21: Beard trimmer | G21: Deodarant | H21: Deodarant | I21: Earbuds | J21: Earbuds | K21: Footwear | L21: Jackets | M21: Mobile | N21: Mobile | O21: Mobile | P21: Shaving cream | Q21: Shaving cream | R21: Smartwatch | S21: Wrist watch
A22: Date | B22: 36533 | C22: 36540 | D22: 36526 | E22: 36536 | F22: 36537 | G22: 36528 | H22: 36544 | I22: 36538 | J22: 36532 | K22: 36531 | L22: 36538 | M22: 36542 | N22: 36535 | O22: 36547 | P22: 36545 | Q22: 36529 | R22: 36531 | S22: 36535
A23: Region | B23: East | C23: South | D23: North | E23: West | F23: West | G23: North | H23: North | I23: South | J23: West | K23: East | L23: South | M23: East | N23: East | O23: West | P23: North | Q23: West | R23: East | S23: North
A24: Price | B24: 2000 | C24: 28000 | D24: 14000 | E24: 36000 | F24: 50000 | G24: 16000 | H24: 18000 | I24: 30000 | J24: 38000 | K24: 4000 | L24: 20000 | M24: 6000 | N24: 8000 | O24: 40000 | P24: 20000 | Q24: 42000 | R24: 10000 | S24: 25000
B27: Lookup values | C27: Region | D27: Price
B28: Bass Headphones | C28: =_xlfn.XLOOKUP(B28,$B$21:$S$21,$B$23:$S$23) -> East | D28: =_xlfn.XLOOKUP(B28,$B$21:$S$21,$B$24:$S$24,"Not there in your data",,1) -> 2000
B29: Earbuds | C29: =_xlfn.XLOOKUP(B29,$B$21:$S$21,$B$23:$S$23) -> South | D29: =_xlfn.XLOOKUP(B29,$B$21:$S$21,$B$24:$S$24,"Not there in your data",,1) -> 30000
B30: Jackets | C30: =_xlfn.XLOOKUP(B30,$B$21:$S$21,$B$23:$S$23) -> South | D30: =_xlfn.XLOOKUP(B30,$B$21:$S$21,$B$24:$S$24,"Not there in your data",,1) -> 20000
B31: Smartwatch | C31: =_xlfn.XLOOKUP(B31,$B$21:$S$21,$B$23:$S$23) -> East | D31: =_xlfn.XLOOKUP(B31,$B$21:$S$21,$B$24:$S$24,"Not there in your data",,1) -> 10000
B32: Perfume | C32: =_xlfn.XLOOKUP(B32,$B$21:$S$21,$B$23:$S$23) -> #N/A | D32: =_xlfn.XLOOKUP(B32,$B$21:$S$21,$B$24:$S$24,"Not there in your data",,1) -> Not there in your data
B42: Items | C42: Date | D42: Region | E42: Price
B43: Bass Headphones | C43: 36533 | D43: East | E43: 2000
B44: Bass Headphones | C44: 36540 | D44: South | E44: 28000
B45: Beard trimmer | C45: 36526 | D45: North | E45: 14000
B46: Beard trimmer | C46: 36536 | D46: West | E46: 36000 | G46: Items | H46: Date | I46: Region | J46: Price
B47: Men's Deodarant | C47: 36528 | D47: North | E47: 16000 | G47: Footwear | H47: {=_xlfn.XLOOKUP(G47,$B$43:$B$58,$C$43:$E$58)} -> 36531 | I47: East | J47: 4000
B48: Women's Deodarant | C48: 36544 | D48: East | E48: 18000 | G48: Shaving cream | H48: {=_xlfn.XLOOKUP(G48,$B$43:$B$58,$C$43:$E$58)} -> 36545 | I48: North | J48: 20000
B49: Earbuds | C49: 36538 | D49: South | E49: 30000 | G49: Deodarant | H49: {=_xlfn.XLOOKUP("*"&G49,$B$43:$B$58,$C$43:$E$58, ,2)} -> 36528 | I49: North | J49: 16000 | K49: wildcard
B50: Earbuds | C50: 36532 | D50: West | E50: 38000 | G50: Shaving | H50: {=_xlfn.XLOOKUP(G50&"*",$B$43:$B$58,$C$43:$E$58, ,2)} -> 36545 | I50: North | J50: 20000
B51: Footwear | C51: 36531 | D51: East | E51: 4000 | G51: Shaving | H51: {=_xlfn.XLOOKUP(G51&"*",$B$43:$B$58,$C$43:$E$58,,2,-1 )} -> 36529 | I51: West | J51: 42000
B52: Jackets | C52: 36538 | D52: South | E52: 20000
B53: Mobile | C53: 36542 | D53: East | E53: 6000
B54: Mobile | C54: 36535 | D54: East | E54: 8000
B55: Shaving cream | C55: 36545 | D55: North | E55: 20000
B56: Shaving brush | C56: 36529 | D56: West | E56: 42000
B57: Smartwatch | C57: 36531 | D57: East | E57: 10000
B58: Wrist watch | C58: 36535 | D58: North | E58: 25000
C63: Year wise prices | G63: Items | H63: Year | I63: Prices | J63: 2-D data
B64: Items | C64: 2018 | D64: 2019 | E64: 2020 | G64: Beard trimmer | H64: 2018 | I64: {=_xlfn.XLOOKUP(G64,B65:B78,_xlfn.XLOOKUP(H64,C64:E64,C65:E78))} -> 40000
B65: Bass Headphones | C65: 36000 | D65: 20000 | E65: 28000 | G65: Mobile | H65: 2020 | I65: {=_xlfn.XLOOKUP(G65,B65:B78,_xlfn.XLOOKUP(H65,C64:E64,C65:E78))} -> 8000
B66: Bass Headphones | C66: 38000 | D66: 30000 | E66: 14000 | G66: Mobile | H66: 2020 | I66: {=_xlfn.XLOOKUP(G66,B65:B78,_xlfn.XLOOKUP(H66,C64:E64,C65:E78))} -> 8000
B67: Beard trimmer | C67: 40000 | D67: 10000 | E67: 36000 | G67: Smartwatch | H67: 2019 | I67: {=_xlfn.XLOOKUP(G67,B65:B78,_xlfn.XLOOKUP(H67,C64:E64,C65:E78))} -> 78000
B68: Beard trimmer | C68: 50000 | D68: 50000 | E68: 16000
B69: Deodarant for men | C69: 20000 | D69: 60000 | E69: 18000
B70: Deodarant for women | C70: 32000 | D70: 70000 | E70: 30000
B71: Earbuds | C71: 89000 | D71: 80000 | E71: 38000
B72: Earbuds | C72: 50000 | D72: 90000 | E72: 4000
B73: Footwear | C73: 2000 | D73: 10000 | E73: 20000
B74: Jackets | C74: 35000 | D74: 2000 | E74: 6000
B75: Mobile | C75: 23000 | D75: 57000 | E75: 8000
B76: Mobile | C76: 56000 | D76: 40000 | E76: 20000
B77: Shaving cream | C77: 4000 | D77: 32000 | E77: 42000
B78: Smartwatch | C78: 36535 | D78: 78000 | E78: 25000

Sheet Sheet11
A3: Row Labels | B3: Sum of Sales | C3: Sum of Quantity
A4: Jan | B4: 1281 | C4: 262
A5: Feb | B5: 1032 | C5: 131
A6: Mar | B6: 958 | C6: 186
A7: Apr | B7: 1155 | C7: 217
A8: May | B8: 1286 | C8: 244
A9: Jun | B9: 1117 | C9: 158
A10: Grand Total | B10: 6829 | C10: 1198

Sheet Sheet4
A1: Date | B1: Region | C1: Product | D1: Sales | E1: Quantity
A2: 45292 | B2: West | C2: Mangoes | D2: 456 | E2: 93
A3: 45301.526 | B3: South | C3: Oranges | D3: 348 | E3: 56
A4: 45311.053 | B4: South | C4: Mangoes | D4: 247 | E4: 76
A5: 45320.579 | B5: West | C5: Apples | D5: 230 | E5: 37
A6: 45330.105 | B6: West | C6: Mangoes | D6: 281 | E6: 50
A7: 45339.632 | B7: West | C7: Oranges | D7: 334 | E7: 52
A8: 45349.158 | B8: South | C8: Apples | D8: 417 | E8: 29
A9: 45358.684 | B9: West | C9: Apples | D9: 441 | E9: 44
A10: 45368.211 | B10: South | C10: Mangoes | D10: 76 | E10: 63
A11: 45377.737 | B11: West | C11: Oranges | D11: 441 | E11: 79
A12: 45387.263 | B12: South | C12: Mangoes | D12: 205 | E12: 23
A13: 45396.789 | B13: West | C13: Oranges | D13: 483 | E13: 97
... A21: 45473 | B21: South | C21: Apples | D21: 319 | E21: 45

Sheet Offset
C3: OFFSET(reference, rows, columns, [height], [width]) | E3: =OFFSET(C6, 0, 3) -> 40 | F3: =OFFSET(C6, 2, 0) -> 9
E4: =OFFSET(C6, 1, 1) -> 7 | F4: =OFFSET(C6, 3, 3) -> 13
B5: B
B6: A | C6: 10 | D6: 20 | E6: 30 | F6: 40
C7: 8 | D7: 7 | E7: 6 | F7: 5
B8: =OFFSET(C6, 0, -1) -> A | C8: 9 | D8: 10 | E8: 11 | F8: 12
B9: =OFFSET(C6, -1, -1) -> B | C9: 16 | D9: 15 | E9: 14 | F9: 13
E16: Sample Data used
D17: 50 | E17: 10 | F17: A
E18: 20 | F18: B
E19: 30 | F19: C
B20: Formulae | C20: Results | E20: 40 | F20: D
B21: OFFSET(C4,0,0) | C21: =OFFSET(E17, 0, 0) -> 10
B22: OFFSET(C4,1,0) | C22: =OFFSET(E17,1,0) -> 20
B23: OFFSET(C4,0,1) | C23: =OFFSET(E17, 0, 1) -> A
B24: OFFSET(C4,1,1) | C24: =OFFSET(E17, 1,1) -> B
B25: OFFSET(D4,0,1) | C25: =OFFSET(E18, 0, 1) -> B
B26: OFFSET(D4,-1,-1) | C26: =OFFSET(E17, 0, -1) -> 50
B27: SUM(OFFSET(C4,0,0,3,1)) | C27: =SUM(OFFSET(E17,0,0,3,1)) -> 60 | D27: =SUM(OFFSET(E17, 0, 0, 4, 1)) -> 100
D32: Months | E32: Sales
D33: Jan | E33: 100
D34: Feb | E34: 200
D35: Mar | E35: 500
D36: Apr | E36: 500
D37: May | E37: 700
D38: June | E38: 2500
D39: July | E39: 500
D40: Aug | E40: 200
D41: Sept | E41: 100
D42: Oct. | E42: 100
D44: Sum of Last 3 rows | E44: =SUM(OFFSET(D32,COUNTA(E32:E42)-3,1,3,1)) -> 400

Sheet Number formatting
E2: Items | F2: Price
E3: Bass Headphones | F3: 2000
E4: Beard trimmer | F4: 14000
B5: 10.55 | C5: 15000 | E5: Deodarant | F5: -16000
B6: 80000000 | C6: 2.5 | E6: Earbuds | F6: 30000
B7: -9500 | C7: -10 | D7: =SUM(B7:C7) -> -9510 | E7: Footwear | F7: 4000
E8: Jackets | F8: 20000
E9: Mobile | F9: 16000
E10: Shaving cream | F10: 20000
E11: Smartwatch | F11: 10000
E12: Wrist watch | F12: 25000

Sheet Date and Time formatting
B2: DATES | C2: TIME
B3: 36528 | C3: 0.85416667
B4: 36526.646 | C4: 0.42013889
B5: 36533
B6: 36537
C7: 1.6805556 | D7: Working hours/ duration/ interval….

Sheet Excel Table
B2: NAMES | C2: SCIENCE | D2: MATH | E2: ENGLISH
B3: Lakshya | C3: 20 | D3: 100 | E3: 70
B4: Karishma | C4: 95 | D4: 89 | E4: 63
B5: Jaya | C5: 80 | D5: 78 | E5: 46
B6: Inder | C6: 79 | D6: 56 | E6: 75
B7: Hitesh | C7: 59 | D7: 68 | E7: 98
B8: Gaurav | C8: 38 | D8: 94 | E8: 24
B9: Fiza | C9: 29 | D9: 80 | E9: 32
B10: Erina | C10: 46 | D10: 75 | E10: 91
B11: Dinesh | C11: 75 | D11: 60 | E11: 78
B12: Chinmay | C12: 80 | D12: 45 | E12: 60
B13: Bunty | C13: 20 | D13: 30 | E13: 50
B14: Arun | C14: 50 | D14: 71 | E14: 80

Sheet Basic Sorting and Filtering
B3: S. No. | C3: First Name | D3: Last Name | F3: Random Numbers
B4: 9 | C4: Rahul | D4: Sharma | F4: 5136779
B5: 2 | C5: Arohi | D5: Sharma | F5: 941521
B6: 5 | C6: Anshu | D6: Poonawala | F6: 85491
B7: 1 | C7: Ananya | D7: Pandey | F7: 74841
B8: 3 | C8: Shashank | D8: Khan | F8: 56165
B9: 7 | C9: Mohan | D9: Kalra | F9: 9515
B10: 8 | C10: Bablu | D10: Gandhi | F10: 4198
B11: 4 | C11: Neil | D11: Armstrong | F11: 851
B12: 6 | C12: Avnish | D12: Agrawal | F12: 814
F13: 489
F14: 81

Sheet Advanced sorting and filtering
C3: S. No. | D3: First Name | E3: Last Name | G3: Random Numbers
C4: 7 | D4: Bablu | E4: Gandhi | G4: 5136779
C5: 2 | D5: Avnish | E5: Agrawal | G5: 81
C6: 9 | D6: Ananya | E6: Pandey | G6: 489
C7: 5 | D7: Anshu | E7: Poonawala | G7: 814
C8: 8 | D8: Arohi | E8: Sharma | G8: 851
C9: 6 | D9: Mohan | E9: Kalra | G9: 4198
C10: 3 | D10: Neil | E10: Armstrong | G10: 9515
C11: 4 | D11: Rahul | E11: Sharma | G11: 56165
C12: 1 | D12: Shashank | E12: Khan | G12: 74841
G13: 85491
G14: 941521
E17: First Name | G17: Last Name
E18: Shashank | G18: Sharma
E19: Anshu | G19: Khan
E23: S. No. | F23: First Name | G23: Last Name
E24: 5 | F24: Anshu | G24: Poonawala
E25: 1 | F25: Shashank | G25: Khan
E27: S. No. | F27: First Name | G27: Last Name
E28: 8 | F28: Arohi | G28: Sharma
E29: 4 | F29: Rahul | G29: Sharma
E30: 1 | F30: Shashank | G30: Khan

Sheet Sheet6
C2: S. No. | D2: First Name | E2: Last Name
C3: 5 | D3: Anshu | E3: Poonawala
C4: 1 | D4: Shashank | E4: Khan

Sheet Removing Duplicates
J1: UNIQUE Function
B2: Employee's Name | C2: Regions | D2: Salary per annum | F2: Employee's Name | G2: Regions | H2: Salary per annum | J2: {=_xlfn.UNIQUE(F2:H18)} -> Employee's Name | K2: Regions | L2: Salary per annum
B3: Aman Sharma | C3: Mumbai | D3: 1000000 | F3: Aman Sharma | G3: Mumbai | H3: 1000000 | J3: Aman Sharma | K3: Mumbai | L3: 1000000
B4: Ishan Saxena | C4: Bhopal | D4: 600000 | F4: Ishan Saxena | G4: Bhopal | H4: 600000 | J4: Ishan Saxena | K4: Bhopal | L4: 600000
B5: Kritika Kumari | C5: Jalandhar | D5: 400000 | F5: Kritika Kumari | G5: Jalandhar | H5: 400000 | J5: Kritika Kumari | K5: Jalandhar | L5: 400000
B6: Mayra khan | C6: Delhi | D6: 200000 | F6: Mayra khan | G6: Delhi | H6: 200000 | J6: Mayra khan | K6: Delhi | L6: 200000
B7: Puneet Singh | C7: Goa | D7: 500000 | F7: Puneet Singh | G7: Goa | H7: 500000 | J7: Puneet Singh | K7: Goa | L7: 500000
B8: Rajnish Gupta | C8: Jhansi | D8: 180000 | F8: Rajnish Gupta | G8: Jhansi | H8: 180000 | J8: Rajnish Gupta | K8: Jhansi | L8: 180000
B9: Pooja Gogia | C9: Kanpur | D9: 350000 | F9: Pooja Gogia | G9: Kanpur | H9: 350000 | J9: Pooja Gogia | K9: Kanpur | L9: 350000
B10: Ashish Singh | C10: Delhi | D10: 225000 | F10: Ashish Singh | G10: Delhi | H10: 225000 | J10: Ashish Singh | K10: Delhi | L10: 225000
B11: Puneet Singh | C11: Goa | D11: 500000 | F11: Puneet Singh | G11: Goa | H11: 500000 | J11: Ayesha khan | K11: Jalandhar | L11: 300000
B12: Ayesha khan | C12: Jalandhar | D12: 300000 | F12: Ayesha khan | G12: Jalandhar | H12: 300000 | J12: Ishan Saxena | K12: Mumbai | L12: 250000
B13: Ashish Singh | C13: Delhi | D13: 225000 | F13: Ashish Singh | G13: Delhi | H13: 225000 | J13: Kritika Kumari | K13: Bhopal | L13: 700000
B14: Ishan Saxena | C14: Mumbai | D14: 250000 | F14: Ishan Saxena | G14: Mumbai | H14: 250000 | J14: Pooja Gupta | K14: Pune | L14: 450000
... B16: Pooja Gupta | C16: Pune | D16: 450000 | F16: Pooja Gupta | G16: Pune | H16: 450000 | J16: Ratan Sharma | K16: Bangalore | L16: 800000
B17: Puneet Singh | C17: Kolkata | D17: 500000 | F17: Puneet Singh | G17: Kolkata | H17: 500000
B18: Ratan Sharma | C18: Bangalore | D18: 800000 | F18: Ratan Sharma | G18: Bangalore | H18: 800000

Sheet Remove duplicates - Table3
A1: Employee's Name | B1: Regions | C1: Salary per annum
A2: Aman Sharma | B2: Mumbai | C2: 1000000
A3: Ishan Saxena | B3: Bhopal | C3: 600000
A4: Kritika Kumari | B4: Jalandhar | C4: 400000
A5: Mayra khan | B5: Delhi | C5: 200000
A6: Puneet Singh | B6: Goa | C6: 500000
A7: Rajnish Gupta | B7: Jhansi | C7: 180000
A8: Pooja Gogia | B8: Kanpur | C8: 350000
A9: Ashish Singh | B9: Delhi | C9: 225000
A10: Ayesha khan | B10: Jalandhar | C10: 300000
A11: Ishan Saxena | B11: Mumbai | C11: 250000
A12: Kritika Kumari | B12: Bhopal | C12: 700000
A13: Pooja Gupta | B13: Pune | C13: 450000
... A15: Ratan Sharma | B15: Bangalore | C15: 800000

Sheet Scenario manager
D2: Mobile Production
D3: Parts | E3: Costing
D4: LCD Screen | E4: 6000
D5: Touchscreen digitizer | E5: 10000
D6: Speakers | E6: 3000
D7: Microphones | E7: 2500
D8: Buttons | E8: 2000
D9: Charging Port | E9: 4500
D10: Antennas | E10: 2500
D11: Sim Card tray | E11: 1000
D12: Earphone Jack | E12: 2000
D13: Vibrating Motor | E13: 7000
D14: Cooling System | E14: 9500
D15: Total | E15: =SUM(E4:E14) -> 50000
D17: Mobile Price | E17: 65000 ?

Sheet Scenario Summary
B2: Scenario Summary
D3: Current Values: | E3: LowerCost | F3: HigherCost
F4: Created by DR. NISHTHA JAIN Modified by DR. NISHTHA JAIN on 20-02-2025
B5: Changing Cells:
C6: screen | D6: 8000 | E6: 6000 | F6: 8000
C7: Digitizer | D7: 7000 | E7: 10000 | F7: 11000
C8: speaker | D8: 5000 | E8: 3000 | F8: 5000
C9: mic | D9: 5000 | E9: 2500 | F9: 5000
C10: $E$8 | D10: 2500 | E10: 2000 | F10: 2500
C11: charg.port | D11: 6000 | E11: 4500 | F11: 6000
C12: antennas | D12: 3000 | E12: 2500 | F12: 3000
C13: simtray | D13: 2500 | E13: 1000 | F13: 2500
C14: $E$12 | D14: 3500 | E14: 2000 | F14: 3500
C15: vibr.motor | D15: 8000 | E15: 7000 | F15: 8000
C16: cooling | D16: 11000 | E16: 9500 | F16: 11000
B17: Result Cells:
C18: $E$15 | D18: 61500 | E18: 50000 | F18: 65500
B19: Notes: Current Values column represents values of changing cells at
B20: time Scenario Summary Report was created. Changing cells for each
B21: scenario are highlighted in gray.

Sheet Scenario PivotTable
A1: $E$4:$E$14 by | B1: (All)
A3: Row Labels | B3: $E$15
A4: HigherCost | B4: 65500
A5: LowerCost | B5: 50000

Sheet Data Table
F1: Charging Port | G1: Total Costing
B2: Mobile Production | G2: =C15 -> 50000
B3: Parts | C3: Costing | F3: 2500 | G3: 47000
B4: LCD Screen | C4: 6000 | F4: 3000 | G4: 47500
B5: Touchscreen digitizer | C5: 10000 | F5: 3500 | G5: 48000
B6: Speakers | C6: 3000 | F6: 4000 | G6: 48500
B7: Microphones | C7: 2500 | F7: 4500 | G7: 49000
B8: Buttons | C8: 2000 | F8: 5000 | G8: 49500
B9: Charging Port | C9: 5500 | F9: 6000 | G9: 50500
B10: Antennas | C10: 4500 | F10: 7000 | G10: 51500
B11: Sim Card tray | C11: 1000 | F11: 8000 | G11: 52500
B12: Earphone Jack | C12: 2000 | F12: 9000 | G12: 53500
B13: Vibrating Motor | C13: 4000 | F13: 10000 | G13: 54500
B14: Cooling System | C14: 9500
B15: Total | C15: =SUM(C4:C14) -> 50000
B26: Sales | C26: 1000 | F26: Unit Price | G26: Total Sales
B27: Unit Price | C27: 20 | G27: =C30 -> 20000
B28: Years | C28: 1 | F28: 10 | G28: 10000
F29: 30 | G29: 30000
B30: Total Amount | C30: =PRODUCT(C26,C27,C28) -> 20000 | F30: 40 | G30: 40000
F31: 50 | G31: 50000
F32: 60 | G32: 60000
F33: 70 | G33: 70000
F34: 80 | G34: 80000
F35: 90 | G35: 90000
F36: 100 | G36: 100000
D40: Total Sales | E40: Years
D41: =C30 -> 20000 | E41: 1 | F41: 2 | G41: 5 | H41: 7 | I41: 10
C42: Unit Price | D42: 10 | E42: 10000 | F42: 20000 | G42: 50000 | H42: 70000 | I42: 100000
D43: 30 | E43: 30000 | F43: 60000 | G43: 150000 | H43: 210000 | I43: 300000
D44: 40 | E44: 40000 | F44: 80000 | G44: 200000 | H44: 280000 | I44: 400000
D45: 50 | E45: 50000 | F45: 100000 | G45: 250000 | H45: 350000 | I45: 500000
D46: 60 | E46: 60000 | F46: 120000 | G46: 300000 | H46: 420000 | I46: 600000
D47: 70 | E47: 70000 | F47: 140000 | G47: 350000 | H47: 490000 | I47: 700000
D48: 80 | E48: 80000 | F48: 160000 | G48: 400000 | H48: 560000 | I48: 800000
D49: 90 | E49: 90000 | F49: 180000 | G49: 450000 | H49: 630000 | I49: 900000
D50: 100 | E50: 100000 | F50: 200000 | G50: 500000 | H50: 700000 | I50: 1000000

Sheet Goal seek - 1
B2: Mobile Production
B3: Parts | C3: Costing
B4: LCD Screen | C4: 6000
B5: Touchscreen digitizer | C5: 10000
B6: Speakers | C6: 3000
B7: Microphones | C7: 2500
B8: Buttons | C8: 2000
B9: Charging Port | C9: 5500
B10: Antennas | C10: 4500
B11: Sim Card tray | C11: 1000
B12: Earphone Jack | C12: 2000
B13: Vibrating Motor | C13: 4000
B14: Cooling System | C14: 9500
B15: Total | C15: =SUM(C4:C14) -> 50000

Sheet Goal Seek - 2
B4: Item | C4: iPhone | F4: Item | G4: iPhone
B5: Price | C5: 100000 | F5: Price | G5: 100000
B6: Down Payment | C6: 40000 | F6: Down Payment | G6: 40000
B7: Tenure | C7: 39.956269 | F7: Tenure | G7: 39.956269
B8: EMI | C8: =(C5-C6)/C7 -> 1501.6417 | D8: YES ! | F8: EMI | G8: 1500 | H8: NO !

Sheet Sales - 2021
A1: SALES | B1: January | C1: February | D1: March | E1: April
A2: Tea | B2: 200 | C2: 50 | D2: 200 | E2: 20
A3: Coffee | B3: 300 | C3: 80 | D3: 300 | E3: 30
A4: Sugar | B4: 600 | C4: 70 | D4: 700 | E4: 50
A5: Milk | B5: 400 | C5: 100 | D5: 900 | E5: 70
A6: Pulses | B6: 700 | C6: 200 | D6: 1000 | E6: 90
A7: Vegetables | B7: 200 | C7: 80 | D7: 500 | E7: 100
A8: Total | B8: =SUM(B2:B7) -> 2400 | C8: =SUM(C2:C7) -> 580 | D8: =SUM(D2:D7) -> 3600 | E8: =SUM(E2:E7) -> 360

Sheet Sales - 2022
B1: SALES | C1: January | D1: February | E1: March | F1: April
B2: Tea | C2: 300 | D2: 100 | E2: 600 | F2: 100
B3: Coffee | C3: 700 | D3: 90 | E3: 500 | F3: 60
B4: Sugar | C4: 400 | D4: 70 | E4: 800 | F4: 70
B5: Milk | C5: 200 | D5: 60 | E5: 10 | F5: 80
B6: Pulses | C6: 100 | D6: 50 | E6: 900 | F6: 90
B7: Vegetables | C7: 600 | D7: 90 | E7: 300 | F7: 100
B8: Total | C8: =SUM(C2:C7) -> 2300 | D8: =SUM(D2:D7) -> 460 | E8: =SUM(E2:E7) -> 3110 | F8: =SUM(F2:F7) -> 500

Sheet Sales - 2023
A3: SALES | B3: January | C3: February | D3: March | E3: April
A4: Tea | B4: 60 | C4: 10 | D4: 60 | E4: 200
A5: Coffee | B5: 70 | C5: 40 | D5: 300 | E5: 300
A6: Sugar | B6: 90 | C6: 70 | D6: 500 | E6: 500
A7: Milk | B7: 100 | C7: 80 | D7: 800 | E7: 800
A8: Pulses | B8: 50 | C8: 60 | D8: 900 | E8: 700
A9: Vegetables | B9: 80 | C9: 30 | D9: 70 | E9: 60
A10: Total | B10: =SUM(B4:B9) -> 450 | C10: =SUM(C4:C9) -> 290 | D10: =SUM(D4:D9) -> 2630 | E10: =SUM(E4:E9) -> 2560

Sheet Sales - 2024
C1: SALES | D1: January | E1: February | F1: March | G1: April
C2: Tea | D2: 100 | E2: 50 | F2: 200 | G2: 10
C3: Coffee | D3: 500 | E3: 80 | F3: 300 | G3: 20
C4: Sugar | D4: 600 | E4: 70 | F4: 700 | G4: 30
C5: Milk | D5: 400 | E5: 100 | F5: 900 | G5: 40
C6: Pulses | D6: 700 | E6: 200 | F6: 1000 | G6: 50
C7: Vegetables | D7: 200 | E7: 80 | F7: 500 | G7: 60
C8: Total | D8: =SUM(D2:D7) -> 2500 | E8: =SUM(E2:E7) -> 580 | F8: =SUM(F2:F7) -> 3600 | G8: =SUM(G2:G7) -> 210

Sheet Consolidate TotalSales
D2: January | E2: February | F2: March | G2: April
C3: Lectures_New | D3: ='Sales - 2021'!$B$2 -> 200 | E3: ='Sales - 2021'!$C$2 -> 50 | F3: ='Sales - 2021'!$D$2 -> 200 | G3: ='Sales - 2021'!$E$2 -> 20
C4: Lectures_New | D4: ='Sales - 2022'!$C$2 -> 300 | E4: ='Sales - 2022'!$D$2 -> 100 | F4: ='Sales - 2022'!$E$2 -> 600 | G4: ='Sales - 2022'!$F$2 -> 100
C5: Lectures_New | D5: ='Sales - 2023'!$B$4 -> 60 | E5: ='Sales - 2023'!$C$4 -> 10 | F5: ='Sales - 2023'!$D$4 -> 60 | G5: ='Sales - 2023'!$E$4 -> 200
C6: Lectures_New | D6: ='Sales - 2024'!$D$2 -> 100 | E6: ='Sales - 2024'!$E$2 -> 50 | F6: ='Sales - 2024'!$F$2 -> 200 | G6: ='Sales - 2024'!$G$2 -> 10
B7: Tea | D7: =SUM(D3:D6) -> 660 | E7: =SUM(E3:E6) -> 210 | F7: =SUM(F3:F6) -> 1060 | G7: =SUM(G3:G6) -> 330 | I7: =TYPE(D7) -> 1
C8: Lectures_New | D8: ='Sales - 2021'!$B$3 -> 300 | E8: ='Sales - 2021'!$C$3 -> 80 | F8: ='Sales - 2021'!$D$3 -> 300 | G8: ='Sales - 2021'!$E$3 -> 30
C9: Lectures_New | D9: ='Sales - 2022'!$C$3 -> 700 | E9: ='Sales - 2022'!$D$3 -> 90 | F9: ='Sales - 2022'!$E$3 -> 500 | G9: ='Sales - 2022'!$F$3 -> 60
C10: Lectures_New | D10: ='Sales - 2023'!$B$5 -> 70 | E10: ='Sales - 2023'!$C$5 -> 40 | F10: ='Sales - 2023'!$D$5 -> 300 | G10: ='Sales - 2023'!$E$5 -> 300
C11: Lectures_New | D11: ='Sales - 2024'!$D$3 -> 500 | E11: ='Sales - 2024'!$E$3 -> 80 | F11: ='Sales - 2024'!$F$3 -> 300 | G11: ='Sales - 2024'!$G$3 -> 20
B12: Coffee | D12: =SUM(D8:D11) -> 1570 | E12: =SUM(E8:E11) -> 290 | F12: =SUM(F8:F11) -> 1400 | G12: =SUM(G8:G11) -> 410
C13: Lectures_New | D13: ='Sales - 2021'!$B$4 -> 600 | E13: ='Sales - 2021'!$C$4 -> 70 | F13: ='Sales - 2021'!$D$4 -> 700 | G13: ='Sales - 2021'!$E$4 -> 50
C14: Lectures_New | D14: ='Sales - 2022'!$C$4 -> 400 | E14: ='Sales - 2022'!$D$4 -> 70 | F14: ='Sales - 2022'!$E$4 -> 800 | G14: ='Sales - 2022'!$F$4 -> 70
C15: Lectures_New | D15: ='Sales - 2023'!$B$6 -> 90 | E15: ='Sales - 2023'!$C$6 -> 70 | F15: ='Sales - 2023'!$D$6 -> 500 | G15: ='Sales - 2023'!$E$6 -> 500
C16: Lectures_New | D16: ='Sales - 2024'!$D$4 -> 600 | E16: ='Sales - 2024'!$E$4 -> 70 | F16: ='Sales - 2024'!$F$4 -> 700 | G16: ='Sales - 2024'!$G$4 -> 30
B17: Sugar | D17: =SUM(D13:D16) -> 1690 | E17: =SUM(E13:E16) -> 280 | F17: =SUM(F13:F16) -> 2700 | G17: =SUM(G13:G16) -> 650
C18: Lectures_New | D18: ='Sales - 2021'!$B$5 -> 400 | E18: ='Sales - 2021'!$C$5 -> 100 | F18: ='Sales - 2021'!$D$5 -> 900 | G18: ='Sales - 2021'!$E$5 -> 70
C19: Lectures_New | D19: ='Sales - 2022'!$C$5 -> 200 | E19: ='Sales - 2022'!$D$5 -> 60 | F19: ='Sales - 2022'!$E$5 -> 10 | G19: ='Sales - 2022'!$F$5 -> 80
C20: Lectures_New | D20: ='Sales - 2023'!$B$7 -> 100 | E20: ='Sales - 2023'!$C$7 -> 80 | F20: ='Sales - 2023'!$D$7 -> 800 | G20: ='Sales - 2023'!$E$7 -> 800
C21: Lectures_New | D21: ='Sales - 2024'!$D$5 -> 400 | E21: ='Sales - 2024'!$E$5 -> 100 | F21: ='Sales - 2024'!$F$5 -> 900 | G21: ='Sales - 2024'!$G$5 -> 40
B22: Milk | D22: =SUM(D18:D21) -> 1100 | E22: =SUM(E18:E21) -> 340 | F22: =SUM(F18:F21) -> 2610 | G22: =SUM(G18:G21) -> 990
C23: Lectures_New | D23: ='Sales - 2021'!$B$6 -> 700 | E23: ='Sales - 2021'!$C$6 -> 200 | F23: ='Sales - 2021'!$D$6 -> 1000 | G23: ='Sales - 2021'!$E$6 -> 90
C24: Lectures_New | D24: ='Sales - 2022'!$C$6 -> 100 | E24: ='Sales - 2022'!$D$6 -> 50 | F24: ='Sales - 2022'!$E$6 -> 900 | G24: ='Sales - 2022'!$F$6 -> 90
C25: Lectures_New | D25: ='Sales - 2023'!$B$8 -> 50 | E25: ='Sales - 2023'!$C$8 -> 60 | F25: ='Sales - 2023'!$D$8 -> 900 | G25: ='Sales - 2023'!$E$8 -> 700
C26: Lectures_New | D26: ='Sales - 2024'!$D$6 -> 700 | E26: ='Sales - 2024'!$E$6 -> 200 | F26: ='Sales - 2024'!$F$6 -> 1000 | G26: ='Sales - 2024'!$G$6 -> 50
B27: Pulses | D27: =SUM(D23:D26) -> 1550 | E27: =SUM(E23:E26) -> 510 | F27: =SUM(F23:F26) -> 3800 | G27: =SUM(G23:G26) -> 930
C28: Lectures_New | D28: ='Sales - 2021'!$B$7 -> 200 | E28: ='Sales - 2021'!$C$7 -> 80 | F28: ='Sales - 2021'!$D$7 -> 500 | G28: ='Sales - 2021'!$E$7 -> 100
C29: Lectures_New | D29: ='Sales - 2022'!$C$7 -> 600 | E29: ='Sales - 2022'!$D$7 -> 90 | F29: ='Sales - 2022'!$E$7 -> 300 | G29: ='Sales - 2022'!$F$7 -> 100
C30: Lectures_New | D30: ='Sales - 2023'!$B$9 -> 80 | E30: ='Sales - 2023'!$C$9 -> 30 | F30: ='Sales - 2023'!$D$9 -> 70 | G30: ='Sales - 2023'!$E$9 -> 60
C31: Lectures_New | D31: ='Sales - 2024'!$D$7 -> 200 | E31: ='Sales - 2024'!$E$7 -> 80 | F31: ='Sales - 2024'!$F$7 -> 500 | G31: ='Sales - 2024'!$G$7 -> 60
B32: Vegetables | D32: =SUM(D28:D31) -> 1080 | E32: =SUM(E28:E31) -> 280 | F32: =SUM(F28:F31) -> 1370 | G32: =SUM(G28:G31) -> 320
C33: Lectures_New | D33: ='Sales - 2021'!$B$8 -> 2400 | E33: ='Sales - 2021'!$C$8 -> 580 | F33: ='Sales - 2021'!$D$8 -> 3600 | G33: ='Sales - 2021'!$E$8 -> 360
C34: Lectures_New | D34: ='Sales - 2022'!$C$8 -> 2300 | E34: ='Sales - 2022'!$D$8 -> 460 | F34: ='Sales - 2022'!$E$8 -> 3110 | G34: ='Sales - 2022'!$F$8 -> 500
C35: Lectures_New | D35: ='Sales - 2023'!$B$10 -> 450 | E35: ='Sales - 2023'!$C$10 -> 290 | F35: ='Sales - 2023'!$D$10 -> 2630 | G35: ='Sales - 2023'!$E$10 -> 2560
C36: Lectures_New | D36: ='Sales - 2024'!$D$8 -> 2500 | E36: ='Sales - 2024'!$E$8 -> 580 | F36: ='Sales - 2024'!$F$8 -> 3600 | G36: ='Sales - 2024'!$G$8 -> 210
B37: Total | D37: =SUM(D33:D36) -> 7650 | E37: =SUM(E33:E36) -> 1910 | F37: =SUM(F33:F36) -> 12940 | G37: =SUM(G33:G36) -> 3630

Sheet Type Check
C2: SALES | D2: January | E2: February | F2: March | G2: April
C3: Tea | D3: 100 | E3: 50 | F3: 200 | G3: 10
C4: Coffee | D4: 500 | E4: 80 | F4: 300 | G4: 20
C5: Sugar | D5: 600 | E5: 70 | F5: 700 | G5: 30
C6: Total | D6: =SUM(D3:D5) -> 1200 | E6: =SUM(E3:E5) -> 200 | F6: =SUM(F3:F5) -> 1200 | G6: =SUM(G3:G5) -> 60
H7: 1 - Number
H8: 2 - Text
B9: =TYPE(D3) -> 1 | H9: 4 - Logical Value
B10: =TYPE(F4) -> 1 | H10: 16 - Error Value
B11: =TYPE(D2) -> 2 | H11: 64 - Array
B12: =TYPE(C2) -> 2 | H12: 128 - Compound Data
B13: =TYPE(C13) -> 4 | C13: TRUE
B14: =TYPE(C14) -> 4 | C14: FALSE
B15: =TYPE(C15) -> 16 | C15: {=SUM} -> #NAME? | E15: {=TYPE(H7:H11)} -> 64 | F15: {=SUM} -> #NAME?
C16: =SUM(F3:G3) -> 210
C17: =SUM(F4:G4) -> 320
B18: {=TYPE(C2:G6)} -> 64

Sheet Approximate & true match
B2: Employee's Name | C2: Graduation score | D2: Salary per annum | G2: Employee's Name | H2: Graduation score | I2: Salary per annum
B3: Aman Sharma | C3: 90 | D3: 600000 | G3: Rajnish Gupta | H3: 30 | I3: 180000
B4: Ishan Saxena | C4: 45 | D4: 250000 | G4: Mayra khan | H4: 35 | I4: 200000
B5: Kritika Kumari | C5: 50 | D5: 400000 | G5: Ashish Singh | H5: 40 | I5: 225000
B6: Mayra khan | C6: 35 | D6: 200000 | G6: Ishan Saxena | H6: 45 | I6: 250000
B7: Puneet Singh | C7: 78 | D7: 500000 | G7: Kritika Kumari | H7: 50 | I7: 400000
B8: Rajnish Gupta | C8: 30 | D8: 180000 | G8: Pooja Gupta | H8: 60 | I8: 450000
B9: Pooja Gupta | C9: 60 | D9: 450000 | G9: Puneet Singh | H9: 78 | I9: 500000
B10: Ashish Singh | C10: 40 | D10: 225000 | G10: Aman Sharma | H10: 90 | I10: 600000
B13: Exact / True match | C13: Employee's Name | D13: Graduation score | E13: Salary per annum | G13: Approximate match | H13: Employee's Name | I13: Graduation score | J13: Salary per annum
C14: Alok Sharma | D14: 25 | E14: =VLOOKUP(D14, C2:D10, 2, 0) -> #N/A | H14: Alok Sharma | I14: 25 | J14: =VLOOKUP(I14, H2:I10, 2, 1) -> #N/A
C15: Puneet Singh | D15: 78 | E15: =VLOOKUP(D15, C2:D10, 2, FALSE) -> 500000 | H15: Puneet Singh | I15: 78 | J15: =VLOOKUP(I15, H2:I10, 2, TRUE) -> 500000
C16: Ishan Saxena | D16: 45 | E16: =VLOOKUP(D16, C2:D10, 2, 0) -> 250000 | H16: Ishan Saxena | I16: 45 | J16: =VLOOKUP(I16, $H$2:$I$10, 2, 1) -> 250000
C17: Rajnish Gupta | D17: 30 | E17: =VLOOKUP(D17, $C$2:$D$10, 2, FALSE) -> 180000 | H17: Rajnish Gupta | I17: 30 | J17: =VLOOKUP(I17, $H$2:$I$10, 2, 1) -> 180000
C18: Garima Singh | D18: 85 | E18: =VLOOKUP(D18, $C$2:$D$10, 2, FALSE) -> #N/A | H18: Garima Singh | I18: 85 | J18: =VLOOKUP(I18, $H$2:$I$10, 2, 1) -> 500000
C19: Aman Sharma | D19: 90 | E19: =VLOOKUP(D19, $C$2:$D$10, 2, FALSE) -> 600000 | H19: Aman Sharma | I19: 90 | J19: =VLOOKUP(I19, $H$2:$I$10, 2, 1) -> 600000
C20: Sayali Desai | D20: 67 | E20: =VLOOKUP(D20, $C$2:$D$10, 2, FALSE) -> #N/A | H20: Sayali Desai | I20: 67 | J20: =VLOOKUP(I20, $H$2:$I$10, 2, 1) -> 450000
C21: Ira Khan | D21: 42 | E21: =VLOOKUP(D21, $C$2:$D$10, 2, FALSE) -> #N/A | H21: Ira Khan | I21: 42 | J21: =VLOOKUP(I21, $H$2:$I$10, 2, 1) -> 225000
C22: Kritika Kumari | D22: 50 | E22: =VLOOKUP(D22, $C$2:$D$10, 2, FALSE) -> 400000 | H22: Kritika Kumari | I22: 50 | J22: =VLOOKUP(I22, $H$2:$I$10, 2, 1) -> 400000
C23: Nikhil Singh | D23: 97 | E23: =VLOOKUP(D23, $C$2:$D$10, 2, FALSE) -> #N/A | H23: Nikhil Singh | I23: 97 | J23: =VLOOKUP(I23, $H$2:$I$10, 2, 1) -> 600000

Sheet Date Time functions
B2: FUNCTIONS
B3: Today
B4: Now | C4: 2024
B5: Date | C5: 8 | E5: Current date | F5: Current time | G5: Today | H5: Now | I5: DATE
B6: Date, Month, Year | C6: 15 | E6: 45691 | F6: 0.74722222 | G6: =TODAY() -> 46015 | H6: =NOW() -> 46015.362 | I6: =DATE(C4, C5, C6) -> 45519
B7: Add/Subtract days
B8: Add/Subtract months | H8: Day | I8: =DAY(I6) -> 15
B9: Dates to days | H9: month | I9: =MONTH(I6) -> 8
B10: Edate | H10: Year | I10: =YEAR(I6) -> 2024
B11: EOMonth
B12: Weekday | E12: Start date | F12: End date | G12: No. of Months | H12: No. of Days
B13: Weeknum | E13: 44927 | F13: 45240 | G13: 2 | H13: 2
B14: Days | E14: 45507 | F14: 44908 | G14: 5 | H14: 5
B15: Datedif | E15: 42348 | F15: 42298 | G15: -5 | H15: -5
B16: Calculate age | E16: 45782 | F16: 46757 | G16: -12 | H16: -12
B17: Networkdays
B18: Networkdays.intl
D20: Edate (add/subtract) | E20: =E13+H13 -> 44929 | F20: =EDATE(E13, G13) -> 44986 | G20: 45301 | H20: 45301 | I20: Dates to Days
E21: =E14+H14 -> 45512 | F21: =EDATE(E14, G14) -> 45660 | G21: 45059 | H21: 45059
E22: =E15+H15 -> 42343 | F22: =EDATE(E15,G15) -> 42195 | G22: 42145 | H22: 42145
E23: =E16+H16 -> 45770 | F23: =EDATE(E16,G16) -> 45417 | G23: 46392 | H23: 46392
D25: EOMONTH | E25: =EOMONTH(E20, 5) -> 45107
E26: =EOMONTH(E21, 3) -> 45626 | G26: 43836
E27: =EOMONTH(E22, 2) -> 42429
E28: =EOMONTH(E23, 4) -> 45900
D30: Weekday | E30: =WEEKDAY(E25,2) -> 5 | F30: 45107
E31: =WEEKDAY(E26, 2) -> 6 | F31: 45626
E32: =WEEKDAY(E27, 2) -> 1 | F32: 42429
E33: =WEEKDAY(E28, 2) -> 7 | F33: 45900
D35: Weeknum | E35: =WEEKNUM(E25,2) -> 27 | F35: 45107
E36: =WEEKNUM(E26,2) -> 48 | F36: 45626
E37: =WEEKNUM(E27,2) -> 10 | F37: 42429
E38: =WEEKNUM(E28,2) -> 35 | F38: 45900
D40: Days | E40: =_xlfn.DAYS(G6, F35) -> 908
E41: =_xlfn.DAYS(G6, F36) -> 389
E42: =_xlfn.DAYS(G6, F37) -> 3586
E43: =_xlfn.DAYS(G6, F38) -> 115
D46: DOB | E46: Years | F46: =DATEDIF(D47, G6, "Y") -> 34
D47: 33463 | E47: Months | F47: =DATEDIF(D47, G6, "M") -> 412
E48: Days | F48: =DATEDIF(D47, G6, "D") -> 12552
B51: Datedifference
B52: Start date | C52: 43831 | D52: 43832 | E52: 43833 | F52: 43834 | G52: 43835 | H52: 43836
B53: End date | C53: 01/12/2021 | D53: 01/12/2021 | E53: 01/12/2021 | F53: 01/12/2021 | G53: 01/12/2021 | H53: 01/12/2021
B54: Units | C54: Y | D54: M | E54: D | F54: MD | G54: YM | H54: YD
B55: Answer | C55: =DATEDIF(C52, C53, "Y") -> 1 | D55: =DATEDIF(D52, D53, "M") -> 22 | E55: =DATEDIF(E52, E53, "D") -> 698 | F55: =DATEDIF(F52, F53, "MD") -> 27 | G55: =DATEDIF(G52, G53, "YM") -> 10 | H55: =DATEDIF(H52, H53, "YD") -> 330
B58: Y | C58: Overall difference in years
B59: M | C59: Overall difference in months | E59: Start date | F59: End date
B60: D | C60: Overall difference in days | E60: 44927 | F60: 45291 | G60: =NETWORKDAYS(E60, F60) -> 260 | H60: =NETWORKDAYS(E60, F60, D67:D69) -> 257 | I60: Networkdays
B61: MD | C61: Exact difference in days, ignores months and years | E61: 45354 | F61: 45639 | G61: =NETWORKDAYS(E61, F61) -> 205 | H61: =NETWORKDAYS(E61, F61, D70:D72) -> 203
B62: YM | C62: Exact difference in months, ignores days and years | E62: 42014 | F62: 42298 | G62: =NETWORKDAYS.INTL(E62, F62) -> 203 | H62: =NETWORKDAYS.INTL(E62, F62, 1, G67:G69) -> 201 | I62: Networkdays.intl
B63: YD | C63: Exact difference in days, ignores years | E63: 45782 | F63: 46757 | I63: <-- Work on it !
D67: 44952 | E67: Republic day | G67: 42030 | H67: Does not work the same for foreign countries
D68: 45153 | E68: Independence Day | G68: 42231
D69: 45201 | E69: Gandhi Jayanti | G69: 42279
D70: 45317 | E70: Republic day
D71: 45519 | E71: Independence Day
D72: 45567 | E72: Gandhi Jayanti

Sheet Basic Conditional formatting
C2: S.No. | D2: Date | E2: Months | F2: Items | G2: Cost Price | H2: Cost Price
C3: 1 | D3: 44576 | E3: February | F3: Pens | G3: 1000 | H3: 5900
C4: 2 | D4: 44562 | E4: March | F4: Colors | G4: 1000 | H4: 1000
C5: 3 | D5: 44572 | E5: April | F5: Highlighters | G5: 1000 | H5: 1000
C6: 4 | D6: 45294 | E6: May | F6: Scales/Rulers | G6: 1000 | H6: 1000
C7: 5 | D7: 44761 | E7: June | F7: Novels | G7: 1200 | H7: 1000
C8: 6 | D8: 44786 | E8: July | F8: Magazines | G8: 1500 | H8: 1200
C9: 7 | D9: 44569 | E9: January | F9: Pencils | G9: 2000 | H9: 1500
C10: 8 | D10: 44568 | E10: January | F10: Pencils | G10: 2200 | H10: 2000
C11: 9 | D11: 44567 | E11: February | F11: Pens | G11: 2300 | H11: 2200
C12: 10 | D12: 45304 | E12: March | F12: Colors | G12: 2800 | H12: 2300
C13: 11 | D13: 44698 | E13: April | F13: Highlighters | G13: 3000 | H13: 2800
C14: 12 | D14: 44691 | E14: May | F14: Scales/Rulers | G14: 3300 | H14: 3000
... C37: 35 | D37: 45972 | E37: July | F37: Magazines | G37: 8900 | H37: 8900
C38: Total

Sheet Advanced Conditional formatting
C2: S.No. | D2: Date | E2: Months | F2: Items | G2: Cost Price | H2: Cost Price | I2: Cost Price
C3: 1 | D3: 44576 | E3: February | F3: Pens | G3: 1000 | H3: 5900 | I3: 5900 | L3: February
C4: 2 | D4: 44562 | E4: March | F4: Colors | G4: 1000 | H4: 7000 | I4: 7000 | L4: 3500
C5: 3 | D5: 44572 | E5: April | F5: Highlighters | G5: 1000 | H5: 3300 | I5: 3300
C6: 4 | D6: 44564 | E6: May | F6: Scales/Rulers | G6: 1000 | H6: 3000 | I6: 3000
C7: 5 | D7: 44761 | E7: June | F7: Novels | G7: 1200 | H7: 4500 | I7: 4500
C8: 6 | D8: 44786 | E8: July | F8: Magazines | G8: 1500 | H8: 4000 | I8: 4000
C9: 7 | D9: 44569 | E9: January | F9: Pencils | G9: 2000 | H9: 2000 | I9: 2000
C10: 8 | D10: 44568 | E10: January | F10: Pencils | G10: 2200 | H10: 1000 | I10: 1000
C11: 9 | D11: 44567 | E11: February | F11: Pens | G11: 2300 | H11: 5300 | I11: 5300
C12: 10 | D12: 44574 | E12: March | F12: Colors | G12: 2800 | H12: 1500 | I12: 1500
C13: 11 | D13: 44698 | E13: April | F13: Highlighters | G13: 3000 | H13: 2800 | I13: 2800
C14: 12 | D14: 44691 | E14: May | F14: Scales/Rulers | G14: 3300 | H14: 8000 | I14: 8000
C15: 13 | D15: 44581 | E15: June | F15: Novels | G15: 3330 | H15: 4000 | I15: 4000
C16: 14 | D16: 44930 | E16: July | F16: Magazines | G16: 3500 | H16: 7800 | I16: 7800
... C37: 35 | D37: 44876 | E37: July | F37: Magazines | G37: 8900 | H37: 5200 | I37: 5200
B42: March
B43: July
B44: Novels
B45: Pens

Sheet Data for Pivot table
B2: Date | C2: Items | D2: Region | E2: Cost Price | F2: Selling Price | G2: Profit / Loss
B3: 38360 | C3: Bass Headphones | D3: East | E3: 2000 | F3: 5000 | G3: =F3-E3 -> 3000
B4: 36531 | C4: Footwear | D4: East | E4: 4000 | F4: 6000 | G4: =F4-E4 -> 2000
B5: 36542 | C5: Mobile | D5: East | E5: 6000 | F5: 8000 | G5: =F5-E5 -> 2000
B6: 36535 | C6: Mobile | D6: North | E6: 8000 | F6: 10000 | G6: =F6-E6 -> 2000
B7: 38052 | C7: Smartwatch | D7: East | E7: 10000 | F7: 20000 | G7: =F7-E7 -> 10000
B8: 36526 | C8: Beard trimmer | D8: North | E8: 14000 | F8: 18000 | G8: =F8-E8 -> 4000
B9: 36528 | C9: Deodarant | D9: North | E9: 16000 | F9: 20000 | G9: =F9-E9 -> 4000
B10: 38461 | C10: Deodarant | D10: North | E10: 18000 | F10: 25000 | G10: =F10-E10 -> 7000
B11: 36545 | C11: Shaving cream | D11: North | E11: 20000 | F11: 28000 | G11: =F11-E11 -> 8000
B12: 36535 | C12: Wrist watch | D12: North | E12: 25000 | F12: 30000 | G12: =F12-E12 -> 5000
B13: 36540 | C13: Bass Headphones | D13: South | E13: 28000 | F13: 30000 | G13: =F13-E13 -> 2000
B14: 39126 | C14: Earbuds | D14: South | E14: 30000 | F14: 38000 | G14: =F14-E14 -> 8000
... B20: 36529 | C20: Shaving cream | D20: West | E20: 42000 | F20: 30000 | G20: =F20-E20 -> -12000

Sheet Pivot grouping
B3: Years | C3: Date | D3: Sum of Selling Price
B4: 2000 | C4: Jan | D4: 332000
B5: 2000 Total | D5: 332000
B7: 2004 | C7: Mar | D7: 20000
B8: 2004 Total | D8: 20000
B10: 2005 | C10: Apr | D10: 25000
B11: 2005 Total | D11: 25000
B13: 2007 | C13: Feb | D13: 38000
B14: 2007 Total | D14: 38000
B16: 2010 | C16: Aug | D16: 55000
B17: 2010 Total | D17: 55000
B19: Grand Total | D19: 470000

Sheet Pivot Table
B3: Sum of Profit / Loss | C3: Column Labels
B4: Row Labels | C4: East | D4: North | E4: South | F4: West | G4: Grand Total
B5: Bass Headphones | C5: 3000 | E5: 2000 | G5: 5000
B6: Beard trimmer | D6: 4000 | F6: -1000 | G6: 3000
B7: Deodarant | D7: 11000 | G7: 11000
B8: Earbuds | E8: 8000 | F8: 4000 | G8: 12000
B9: Footwear | C9: 2000 | G9: 2000
B10: Jackets | E10: 20000 | G10: 20000
B11: Mobile | C11: 2000 | D11: 2000 | F11: -5000 | G11: -1000
B12: Shaving cream | D12: 8000 | F12: -12000 | G12: -4000
B13: Smartwatch | C13: 10000 | G13: 10000
B14: Wrist watch | D14: 5000 | G14: 5000
B15: Grand Total | C15: 17000 | D15: 30000 | E15: 30000 | F15: -14000 | G15: 63000

Sheet Pivot Table 2
B3: Row Labels | C3: Sum of Selling Price
B4: West | C4: 192000
B5: Beard trimmer | C5: 85000
B6: Earbuds | C6: 42000
B7: Mobile | C7: 35000
B8: Shaving cream | C8: 30000
B10: Grand Total | C10: 192000

Sheet Data for Pivot chart
C2: Date | D2: Items | E2: Region | F2: Cost Price | G2: Selling Price | H2: Profit / Loss
C3: 36533 | D3: Bass Headphones | E3: East | F3: 2000 | G3: 5000 | H3: =G3-F3 -> 3000
C4: 36531 | D4: Footwear | E4: East | F4: 4000 | G4: 15000 | H4: =G4-F4 -> 11000
C5: 36542 | D5: Mobile | E5: East | F5: 6000 | G5: 8000 | H5: =G5-F5 -> 2000
C6: 36535 | D6: Mobile | E6: North | F6: 8000 | G6: 10000 | H6: =G6-F6 -> 2000
C7: 38052 | D7: Smartwatch | E7: East | F7: 10000 | G7: 20000 | H7: =G7-F7 -> 10000
C8: 36526 | D8: Beard trimmer | E8: North | F8: 14000 | G8: 18000 | H8: =G8-F8 -> 4000
C9: 36528 | D9: Deodarant | E9: North | F9: 16000 | G9: 20000 | H9: =G9-F9 -> 4000
C10: 38461 | D10: Deodarant | E10: North | F10: 18000 | G10: 25000 | H10: =G10-F10 -> 7000
C11: 36545 | D11: Shaving cream | E11: North | F11: 20000 | G11: 28000 | H11: =G11-F11 -> 8000
C12: 36535 | D12: Wrist watch | E12: North | F12: 25000 | G12: 50000 | H12: =G12-F12 -> 25000
C13: 36540 | D13: Bass Headphones | E13: South | F13: 28000 | G13: 30000 | H13: =G13-F13 -> 2000
C14: 39126 | D14: Earbuds | E14: South | F14: 30000 | G14: 38000 | H14: =G14-F14 -> 8000
... C20: 36529 | D20: Shaving cream | E20: West | F20: 42000 | G20: 30000 | H20: =G20-F20 -> -12000

Sheet Pivot Chart
B1: Row Labels | C1: Sum of Selling Price
B2: East | C2: 48000
B3: Bass Headphones | C3: 5000
B4: Footwear | C4: 15000
B5: Mobile | C5: 8000
B6: Smartwatch | C6: 20000
B7: North | C7: 151000
B8: Beard trimmer | C8: 18000
B9: Deodarant | C9: 45000
B10: Mobile | C10: 10000
B11: Shaving cream | C11: 28000
B12: Wrist watch | C12: 50000
B13: South | C13: 108000
... B22: Grand Total | C22: 499000

Sheet Pivot Slicer
B2: Row Labels | C2: Sum of Selling Price
B3: East | C3: 39000
B4: Bass Headphones | C4: 5000
B5: Footwear | C5: 6000
B6: Mobile | C6: 8000
B7: Smartwatch | C7: 20000
B8: North | C8: 131000
B9: Beard trimmer | C9: 18000
B10: Deodarant | C10: 45000
B11: Mobile | C11: 10000
B12: Shaving cream | C12: 28000
B13: Wrist watch | C13: 30000
B14: South | C14: 108000
... B23: Grand Total | C23: 470000

Sheet Pivot Timeline
A3: Sum of Selling Price | B3: Column Labels
A4: Row Labels | B4: East | C4: North | D4: South | E4: West | F4: Grand Total
A5: Bass Headphones | B5: 5000 | D5: 30000 | F5: 35000
A6: Beard trimmer | C6: 18000 | E6: 85000 | F6: 103000
A7: Deodarant | C7: 45000 | F7: 45000
A8: Earbuds | D8: 38000 | E8: 42000 | F8: 80000
A9: Footwear | B9: 6000 | F9: 6000
A10: Jackets | D10: 40000 | F10: 40000
A11: Mobile | B11: 8000 | C11: 10000 | E11: 35000 | F11: 53000
A12: Shaving cream | C12: 28000 | E12: 30000 | F12: 58000
A13: Smartwatch | B13: 20000 | F13: 20000
A14: Wrist watch | C14: 30000 | F14: 30000
A15: Grand Total | B15: 39000 | C15: 131000 | D15: 108000 | E15: 192000 | F15: 470000

Sheet Charts - Column, Clustered, Pie
A2: Employee's Name | B2: Salary per annum
A3: Rajnish Gupta | B3: 180000
A4: Mayra khan | B4: 200000
A5: Ashish Singh | B5: 225000
A6: Ishan Saxena | B6: 250000
A7: Kritika Kumari | B7: 400000
A8: Pooja Gupta | B8: 450000
A9: Puneet Singh | B9: 500000
A10: Ajeet Sharma | B10: 600000
A41: Employee's Name | B41: Salary per annum | C41: Previous salaries
A42: Aman Sharma | B42: 600000 | C42: 300000
A43: Ishan Saxena | B43: 250000 | C43: 100000
A44: Kritika Kumari | B44: 400000 | C44: 500000
A45: Mayra khan | B45: 200000 | C45: 600000
A46: Puneet Singh | B46: 500000 | C46: 800000
A47: Rajnish Gupta | B47: 180000 | C47: 70000
A48: Pooja Gupta | B48: 450000 | C48: 800000
A49: Ashish Singh | B49: 225000 | C49: 400000

Sheet Charts - Line, Clustered bar
B2: Years | C2: Selling Price
B3: 1990 | C3: 5000
B4: 1991 | C4: 6000
B5: 1992 | C5: 8000
B6: 1993 | C6: 10000
B7: 1994 | C7: 20000
B8: 1995 | C8: 18000
B9: 1996 | C9: 20000
B10: 1997 | C10: 25000
B11: 1998 | C11: 28000
B12: 1999 | C12: 30000
B13: 2000 | C13: 30000
B14: 2001 | C14: 38000
... B20: 2007 | C20: 30000
B52: Years | C52: Selling Price
B53: 1990 | C53: 5000
B54: 1991 | C54: 6000
B55: 1992 | C55: 8000
B56: 1993 | C56: 10000
B57: 1994 | C57: 20000
B58: 1995 | C58: 18000
B59: 1996 | C59: 20000
B60: 1997 | C60: 25000
B61: 1998 | C61: 28000
B62: 1999 | C62: 30000
B63: 2000 | C63: 30000
B64: 2001 | C64: 38000
... B70: 2007 | C70: 30000
B127: Date | C127: Items | D127: Region | E127: Cost Price | F127: Selling Price | G127: Profit / Loss
B128: 36533 | C128: Bass Headphones | D128: East | E128: 2000 | F128: 5000 | G128: =F128-E128 -> 3000
B129: 36531 | C129: Footwear | D129: East | E129: 4000 | F129: 6000 | G129: =F129-E129 -> 2000
B130: 36542 | C130: Mobile | D130: East | E130: 6000 | F130: 8000 | G130: =F130-E130 -> 2000
B131: 36535 | C131: Mobile | D131: North | E131: 8000 | F131: 10000 | G131: =F131-E131 -> 2000
B132: 36531 | C132: Smartwatch | D132: East | E132: 10000 | F132: 20000 | G132: =F132-E132 -> 10000
B133: 36526 | C133: Beard trimmer | D133: North | E133: 14000 | F133: 18000 | G133: =F133-E133 -> 4000
B134: 36528 | C134: Deodarant | D134: North | E134: 16000 | F134: 20000 | G134: =F134-E134 -> 4000
B135: 36544 | C135: Deodarant | D135: North | E135: 18000 | F135: 25000 | G135: =F135-E135 -> 7000
B136: 36545 | C136: Shaving cream | D136: North | E136: 20000 | F136: 28000 | G136: =F136-E136 -> 8000
B137: 36535 | C137: Wrist watch | D137: North | E137: 25000 | F137: 30000 | G137: =F137-E137 -> 5000
B138: 36540 | C138: Bass Headphones | D138: South | E138: 28000 | F138: 30000 | G138: =F138-E138 -> 2000
B139: 36538 | C139: Earbuds | D139: South | E139: 30000 | F139: 38000 | G139: =F139-E139 -> 8000
... B145: 36529 | C145: Shaving cream | D145: West | E145: 42000 | F145: 30000 | G145: =F145-E145 -> -12000

Sheet Charts - Sprklne, Wtrf, Fnnl
A2: Employee's Name | B2: Salary per annum
A3: Rajnish Gupta | B3: 180000
A4: Mayra khan | B4: 200000
A5: Ashish Singh | B5: 225000 | D5: Employee's Name | E5: Salary per annum | F5: Previous Salaries
A6: Ishan Saxena | B6: 250000 | D6: Rajnish Gupta | E6: 180000 | F6: 90000
A7: Kritika Kumari | B7: 400000 | D7: Mayra khan | E7: 200000 | F7: 40000
A8: Pooja Gupta | B8: 450000 | D8: Ashish Singh | E8: 225000 | F8: -50000
A9: Puneet Singh | B9: 500000 | D9: Ishan Saxena | E9: 250000 | F9: 35000
A10: Ajeet Sharma | B10: -600000 | D10: Kritika Kumari | E10: 400000 | F10: 78000
D11: Pooja Gupta | E11: 450000 | F11: 30000
D12: Puneet Singh | E12: 500000 | F12: -60000
D13: Aman Sharma | E13: 600000 | F13: 48000
D14: Line | G14: Sparklines
D15: Column
D16: Win/Loss
A42: Employee's Name | B42: Salary per annum | C42: Previous Salaries
A43: Rajnish Gupta | B43: 180000 | C43: 90000
A44: Mayra khan | B44: 200000 | C44: 40000
A45: Ashish Singh | B45: 225000 | C45: -50000
A46: Ishan Saxena | B46: 250000 | C46: 35000
A47: Kritika Kumari | B47: 400000 | C47: 78000
A48: Pooja Gupta | B48: 450000 | C48: 30000
A49: Puneet Singh | B49: 500000 | C49: -60000
A50: Aman Sharma | B50: 600000 | C50: 48000

Sheet Charts - Treemap, Sunburst
G1: Items | H1: Region | I1: Cost Price
G2: Bass Headphones | H2: East | I2: 2000
G3: Footwear | H3: East | I3: 4000
G4: Mobile | H4: East | I4: 6000
G5: Mobile | H5: North | I5: 8000
G6: Smartwatch | H6: East | I6: 10000
G7: Beard trimmer | H7: North | I7: 14000
G8: Deodarant | H8: North | I8: 16000
G9: Deodarant | H9: North | I9: 18000
G10: Shaving cream | H10: North | I10: 20000
G11: Wrist watch | H11: North | I11: 20000
G12: Bass Headphones | H12: South | I12: 25000
G13: Earbuds | H13: South | I13: 28000
... G19: Shaving cream | H19: West | I19: 50000
I54: Items | J54: Region | K54: Cost Price
I55: Bass Headphones | J55: East | K55: 2000
I56: Footwear | J56: East | K56: 4000
I57: Mobile | J57: East | K57: 6000
I58: Mobile | J58: South | K58: 8000
I59: Smartwatch | J59: East | K59: 10000
I60: Beard trimmer | J60: North | K60: 14000
I61: Deodarant | J61: North | K61: 16000
I62: Deodarant | J62: North | K62: 18000
I63: Shaving cream | J63: North | K63: 20000
I64: Wrist watch | J64: North | K64: 25000
I65: Bass Headphones | J65: South | K65: 28000
I66: Earbuds | J66: South | K66: 30000
... I72: Shaving cream | J72: West | K72: 42000

Sheet Unclean data
B2: Customer ID | C2: No. of items ordered | D2: Revenue | E2: Cost | F2: Order Status
B3: 152689 - Bake and Shake | C3: 329 | D3: 1645 | E3: 822.5 | F3: Open
B4: 985245 - Small bites | C4: 350 | D4: 1750 | E4: 875 | F4: Open
B5: 785432 - Meet and Eat | C5: 981 | D5: 4905 | E5: 2452.5 | F5: Open
B6: 152689 - Bake and Shake | C6: 843 | D6: 4215 | E6: 2107.5 | F6: Open
B7: 985245 - Small bites | C7: 154 | D7: 770 | E7: 385 | F7: Open
B8: 785432 - Meet and Eat | C8: 993 | D8: 4965 | E8: 2482.5 | F8: Open
B9: 152689 - Bake and Shake | C9: 99 | D9: 495 | E9: 247.5 | F9: Open
B10: 325698 - Cascade Grovers | C10: 747 | D10: 3735 | E10: 1867.5 | F10: Open
B11: 985245 - Small bites | C11: 817 | D11: 4085 | E11: 2042.5 | F11: Open
B12: 785432 - Meet and Eat | C12: 798 | D12: 3990 | E12: 1995 | F12: Open
B13: 152689 - Bake and Shake | C13: 680 | D13: 3400 | E13: 1700 | F13: Open
B14: 325698 - Cascade Grovers | C14: 383 | D14: 1915 | E14: 957.5 | F14: Open
... B16: 985245 - Small bites | C16: 77 | D16: 385 | E16: 192.5 | F16: Delivered
B17: 152689 - Bake and Shake | C17: 910 | D17: 4550 | F17: Delivered
B18: 325698 - Cascade Grovers | C18: 300 | D18: 1500 | E18: 750 | F18: Delivered
B19: 325698 - Cascade Grovers | C19: 511 | D19: 2555 | E19: 1277.5 | F19: Delivered
B20: 785432 - Meet and Eat | C20: 868 | D20: 4340 | E20: 2170 | F20: Delivered
B21: 452584 - FInd yours | C21: 211 | D21: 1055 | E21: 527.5 | F21: Delivered
B22: 985245 - Small bites | C22: 549 | D22: 2745 | E22: 1372.5 | F22: Delivered
B23: 985245 - Small bites | C23: 469 | D23: 2345 | F23: Delivered
B24: 985245 - Small bites | D24: 3505 | E24: 1752.5 | F24: Delivered
B25: 785432 - Meet and Eat | C25: 198 | D25: 990 | E25: 495 | F25: Delivered
B26: 452584 - FInd yours | C26: 415 | D26: 2075 | E26: 1037.5 | F26: Delivered
B27: 152689 - Bake and Shake | C27: 995 | D27: 4975 | E27: 2487.5 | F27: Delivered
B28: 985245 - Small bites | C28: 205 | D28: 1025 | F28: Delivered
B29: 985245 - Small bites | C29: 154 | D29: 770 | E29: 385 | F29: Delivered
B30: 152689 - Bake and Shake | C30: 236 | D30: 1180 | F30: Delivered
B31: 452584 - FInd yours | C31: 73 | D31: 365 | E31: 182.5 | F31: Delivered
B32: 985245 - Small bites | C32: 736 | D32: 3680 | E32: 1840 | F32: Delivered
B33: 985245 - Small bites | D33: 1300 | E33: 650 | F33: Delivered
B34: 785432 - Meet and Eat | C34: 509 | D34: 2545 | E34: 1272.5 | F34: Delivered
B35: 785432 - Meet and Eat | C35: 381 | D35: 1905 | E35: 952.5 | F35: Delivered
B36: 985245 - Small bites | C36: 974 | D36: 4870 | E36: 2435 | F36: Delivered
B37: 985245 - Small bites | C37: 727 | D37: 3635 | E37: 1817.5 | F37: Delivered
B38: 985245 - Small bites | C38: 162 | D38: 810 | E38: 405 | F38: Delivered
B39: 785432 - Meet and Eat | C39: 572 | D39: 2860 | E39: 1430 | F39: Delivered
B40: 785432 - Meet and Eat | C40: 373 | D40: 1865 | E40: 932.5 | F40: Delivered
B41: 785432 - Meet and Eat | D41: 1620 | E41: 810 | F41: Delivered
B42: 152689 - Bake and Shake | C42: 203 | D42: 1015 | E42: 507.5 | F42: Delivered
B43: 152689 - Bake and Shake | C43: 313 | D43: 1565 | F43: Delivered
B44: 152689 - Bake and Shake | C44: 745 | D44: 3725 | F44: Delivered
B45: 452584 - FInd yours | C45: 819 | D45: 4095 | E45: 2047.5 | F45: Delivered
B46: 325698 - Cascade Grovers | C46: 983 | D46: 4915 | E46: 2457.5 | F46: Delivered
B47: 985245 - Small bites | C47: 223 | D47: 1115 | E47: 557.5 | F47: Delivered
B48: 985245 - Small bites | C48: 230 | D48: 1150 | E48: 575 | F48: Delivered
B49: 325698 - Cascade Grovers | C49: 346 | D49: 1730 | F49: Delivered
B50: 152689 - Bake and Shake | C50: 958 | D50: 4790 | E50: 2395 | F50: Delivered
B51: 985245 - Small bites | C51: 58 | D51: 290 | E51: 145 | F51: Delivered
B52: 152689 - Bake and Shake | C52: 500 | D52: 2500 | E52: 1250 | F52: Delivered
B53: 785432 - Meet and Eat | C53: 344 | D53: 1720 | E53: 860 | F53: Delivered
B54: 325698 - Cascade Grovers | C54: 541 | D54: 2705 | E54: 1352.5 | F54: Delivered
B55: 985245 - Small bites | C55: 792 | D55: 3960 | F55: Delivered
B56: 452584 - FInd yours | C56: 385 | D56: 1925 | E56: 962.5 | F56: Delivered
B57: 325698 - Cascade Grovers | C57: 614 | D57: 3070 | E57: 1535 | F57: Delivered
B58: 785432 - Meet and Eat | C58: 703 | D58: 3515 | E58: 1757.5 | F58: Delivered
B59: 152689 - Bake and Shake | C59: 799 | D59: 3995 | E59: 1997.5 | F59: Delivered
B60: 325698 - Cascade Grovers | D60: 4905 | E60: 2452.5 | F60: Delivered
B61: 985245 - Small bites | C61: 854 | D61: 4270 | E61: 2135 | F61: Delivered
B62: 325698 - Cascade Grovers | C62: 929 | D62: 4645 | F62: Delivered
B63: 985245 - Small bites | C63: 906 | D63: 4530 | E63: 2265 | F63: Delivered
B64: 785432 - Meet and Eat | C64: 467 | D64: 2335 | E64: 1167.5 | F64: Delivered
B65: 152689 - Bake and Shake | C65: 133 | D65: 665 | E65: 332.5 | F65: Delivered
B66: 325698 - Cascade Grovers | C66: 587 | D66: 2935 | E66: 1467.5 | F66: Delivered
B67: 985245 - Small bites | C67: 648 | D67: 3240 | E67: 1620 | F67: Delivered
B68: 785432 - Meet and Eat | C68: 832 | D68: 4160 | E68: 2080 | F68: Delivered
B69: 325698 - Cascade Grovers | C69: 733 | D69: 3665 | E69: 1832.5 | F69: Delivered
B70: 985245 - Small bites | C70: 154 | D70: 770 | E70: 385 | F70: Delivered
B71: 985245 - Small bites | C71: 77 | D71: 385 | E71: 192.5 | F71: Delivered
B72: 785432 - Meet and Eat | C72: 784 | D72: 3920 | E72: 1960 | F72: Delivered
B73: 152689 - Bake and Shake | C73: 82 | D73: 410 | E73: 205 | F73: Delivered
B74: 452584 - FInd yours | C74: 530 | D74: 2650 | E74: 1325 | F74: Delivered
... B79: 985245 - Small bites | C79: 856 | D79: 4280 | E79: 2140 | F79: Delivered
B80: 152689 - Bake and Shake | D80: 4440 | E80: 2220 | F80: Delivered
B81: 325698 - Cascade Grovers | C81: 914 | D81: 4570 | E81: 2285 | F81: Delivered
B82: 985245 - Small bites | C82: 275 | D82: 1375 | E82: 687.5 | F82: Delivered
B83: 985245 - Small bites | C83: 669 | D83: 3345 | E83: 1672.5 | F83: Delivered
B84: 985245 - Small bites | C84: 344 | D84: 1720 | E84: 860 | F84: Delivered
B85: 985245 - Small bites | C85: 389 | D85: 1945 | E85: 972.5 | F85: Delivered
B86: 785432 - Meet and Eat | D86: 3150 | E86: 1575 | F86: Delivered
B87: 325698 - Cascade Grovers | C87: 344 | D87: 1720 | E87: 860 | F87: Delivered
B88: 985245 - Small bites | C88: 941 | D88: 4705 | E88: 2352.5 | F88: Delivered
B89: 985245 - Small bites | C89: 287 | D89: 1435 | E89: 717.5 | F89: Delivered
B90: 452584 - FInd yours | C90: 994 | D90: 4970 | E90: 2485 | F90: Delivered
B91: 325698 - Cascade Grovers | C91: 598 | D91: 2990 | E91: 1495 | F91: Delivered

Sheet Power Query - Cleaned data
A1: S. No. | B1: Restaurant IDs | C1: Restaurant names | D1: No. of items ordered | E1: Billing amounts | F1: Order Status
A2: 1 | B2: 985245 | C2: Small bites | D2: 58 | E2: 290 | F2: Completed
A3: 2 | B3: 452584 | C3: FInd yours | D3: 73 | E3: 365 | F3: Completed
A4: 3 | B4: 985245 | C4: Small bites | D4: 77 | E4: 385 | F4: Completed
A5: 4 | B5: 985245 | C5: Small bites | D5: 77 | E5: 385 | F5: Completed
A6: 5 | B6: 152689 | C6: Bake and Shake | D6: 82 | E6: 410 | F6: Completed
A7: 6 | B7: 152689 | C7: Bake and Shake | D7: 99 | E7: 495 | F7: Open
A8: 7 | B8: 152689 | C8: Bake and Shake | D8: 133 | E8: 665 | F8: Completed
A9: 8 | B9: 985245 | C9: Small bites | D9: 154 | E9: 770 | F9: Completed
A10: 9 | B10: 985245 | C10: Small bites | D10: 154 | E10: 770 | F10: Open
A11: 10 | B11: 985245 | C11: Small bites | D11: 154 | E11: 770 | F11: Completed
A12: 11 | B12: 985245 | C12: Small bites | D12: 162 | E12: 810 | F12: Completed
A13: 12 | B13: 785432 | C13: Meet and Eat | D13: 198 | E13: 990 | F13: Completed
... A83: 88 | B83: 152689 | C83: Bake and Shake | D83: 995 | E83: 4975 | F83: Completed

Sheet Power Query Merge.
A1: Date | B1: Items | C1: Region | D1: Cost Price | E1: Selling Price
A2: 36533 | B2: Bass Headphones | C2: East | D2: 2000 | E2: 5000
A3: 36531 | B3: Footwear | C3: East | D3: 4000 | E3: 6000
A4: 36542 | B4: Mobile | C4: East | D4: 6000 | E4: 8000
A5: 36535 | B5: Mobile | C5: North | D5: 8000 | E5: 10000
A6: 38052 | B6: Smartwatch | C6: East | D6: 10000 | E6: 20000
A7: 36526 | B7: Beard trimmer | C7: North | D7: 14000 | E7: 18000
A8: 36528 | B8: Deodarant | C8: North | D8: 16000 | E8: 20000
A9: 38461 | B9: Deodarant | C9: North | D9: 18000 | E9: 25000
A10: 36545 | B10: Shaving cream | C10: North | D10: 20000 | E10: 28000
A11: 36545 | B11: Shaving cream | C11: North | D11: 20000 | E11: 40000
A12: 36538 | B12: Jackets | C12: South | D12: 20000 | E12: 28000
A13: 36538 | B13: Jackets | C13: South | D13: 20000 | E13: 40000
... A21: 36529 | B21: Shaving cream | C21: West | D21: 42000 | E21: 30000

Sheet Table1
A1: Cost Price | B1: Selling Price
A2: 2000 | B2: 5000
A3: 4000 | B3: 6000
A4: 6000 | B4: 8000
A5: 8000 | B5: 10000
A6: 10000 | B6: 20000
A7: 14000 | B7: 18000
A8: 16000 | B8: 20000
A9: 18000 | B9: 25000
A10: 20000 | B10: 28000
A11: 25000 | B11: 30000
A12: 28000 | B12: 30000
A13: 30000 | B13: 38000
... A19: 42000 | B19: 30000

Sheet Table2
A1: Date | B1: Items | C1: Region | D1: Cost Price
A2: 36533 | B2: Bass Headphones | C2: East | D2: 2000
A3: 36531 | B3: Footwear | C3: East | D3: 4000
A4: 36542 | B4: Mobile | C4: East | D4: 6000
A5: 36535 | B5: Mobile | C5: North | D5: 8000
A6: 38052 | B6: Smartwatch | C6: East | D6: 10000
A7: 36526 | B7: Beard trimmer | C7: North | D7: 14000
A8: 36528 | B8: Deodarant | C8: North | D8: 16000
A9: 38461 | B9: Deodarant | C9: North | D9: 18000
A10: 36545 | B10: Shaving cream | C10: North | D10: 20000
A11: 36535 | B11: Wrist watch | C11: North | D11: 25000
A12: 36540 | B12: Bass Headphones | C12: South | D12: 28000
A13: 39126 | B13: Earbuds | C13: South | D13: 30000
... A19: 36529 | B19: Shaving cream | C19: West | D19: 42000

Sheet Append1
A1: Date | B1: Items | C1: Region | D1: Cost Price | E1: Selling Price | F1: Profit / Loss
A2: 36533 | B2: Bass Headphones | C2: East | D2: 2000 | E2: 5000 | F2: 3000
A3: 36531 | B3: Footwear | C3: East | D3: 4000 | E3: 6000 | F3: 2000
A4: 36542 | B4: Mobile | C4: East | D4: 6000 | E4: 8000 | F4: 2000
A5: 36535 | B5: Mobile | C5: North | D5: 8000 | E5: 10000 | F5: 2000
A6: 38052 | B6: Smartwatch | C6: East | D6: 10000 | E6: 20000 | F6: 10000
A7: 36526 | B7: Beard trimmer | C7: North | D7: 14000 | E7: 18000 | F7: 4000
A8: 36528 | B8: Deodarant | C8: North | D8: 16000 | E8: 20000 | F8: 4000
A9: 38461 | B9: Deodarant | C9: North | D9: 18000 | E9: 25000 | F9: 7000
A10: 36545 | B10: Shaving cream | C10: North | D10: 20000 | E10: 28000 | F10: 8000
A11: 36535 | B11: Wrist watch | C11: North | D11: 25000 | E11: 30000 | F11: 5000
A12: 36540 | B12: Bass Headphones | C12: South | D12: 28000 | E12: 30000 | F12: 2000
A13: 39126 | B13: Earbuds | C13: South | D13: 30000 | E13: 38000 | F13: 8000
... A19: 36529 | B19: Shaving cream | C19: West | D19: 42000 | E19: 30000 | F19: -12000

Sheet Sheet5
A1: Date | B1: Items | C1: Region | D1: Cost Price | E1: Selling Price | F1: Profit / Loss
A2: 36538 | B2: Jackets | C2: South | D2: 20000 | E2: 40000 | F2: 20000
A3: 36536 | B3: Beard trimmer | C3: West | D3: 36000 | E3: 30000 | F3: -6000
A4: 40402 | B4: Beard trimmer | C4: West | D4: 50000 | E4: 55000 | F4: 5000
A5: 36532 | B5: Earbuds | C5: West | D5: 38000 | E5: 42000 | F5: 4000
A6: 36547 | B6: Mobile | C6: West | D6: 40000 | E6: 35000 | F6: -5000
A7: 36529 | B7: Shaving cream | C7: West | D7: 42000 | E7: 30000 | F7: -12000

Sheet Sheet2
A1: Date | B1: Items | C1: Region | D1: Cost Price | E1: Selling Price | F1: Profit / Loss
A2: 36528 | B2: Deodarant | C2: North | D2: 16000 | E2: 20000 | F2: 4000
A3: 38461 | B3: Deodarant | C3: North | D3: 18000 | E3: 25000 | F3: 7000
A4: 36545 | B4: Shaving cream | C4: North | D4: 20000 | E4: 28000 | F4: 8000
A5: 36535 | B5: Wrist watch | C5: North | D5: 25000 | E5: 30000 | F5: 5000
A6: 36540 | B6: Bass Headphones | C6: South | D6: 28000 | E6: 30000 | F6: 2000
A7: 39126 | B7: Earbuds | C7: South | D7: 30000 | E7: 38000 | F7: 8000

Sheet Sheet1
A1: Date | B1: Items | C1: Region | D1: Cost Price | E1: Selling Price | F1: Profit / Loss
A2: 36533 | B2: Bass Headphones | C2: East | D2: 2000 | E2: 5000 | F2: 3000
A3: 36531 | B3: Footwear | C3: East | D3: 4000 | E3: 6000 | F3: 2000
A4: 36542 | B4: Mobile | C4: East | D4: 6000 | E4: 8000 | F4: 2000
A5: 36535 | B5: Mobile | C5: North | D5: 8000 | E5: 10000 | F5: 2000
A6: 38052 | B6: Smartwatch | C6: East | D6: 10000 | E6: 20000 | F6: 10000
A7: 36526 | B7: Beard trimmer | C7: North | D7: 14000 | E7: 18000 | F7: 4000

Sheet Unclean sales data
C2: * This Sales dataset for different products is collected from a renowned store in Mumbai. * It should be used to answer all the questions correctly. * The dataset contains the names of different products and their selling prices for 5 years.
B5: Sales of 7 products across 5 years
B6: Products | C6: 2012 | D6: 2013 | E6: 2014 | F6: 2015 | G6: 2016
B7: Antiques | C7: 432521 | D7: 227724 | E7: 530619 | F7: 182911 | G7: 182000
B9: Bottles | C9: 44244 | D9: 310416 | F9: 92490 | G9: 921000
B10: Cars | C10: 433796 | D10: 191447 | E10: 18073 | F10: 484888 | G10: 484000
B11: Fish Aquarium | C11: 50000 | D11: 60000 | E11: 30000 | G11: 87494
B13: Drones | C13: 539770 | D13: 125314 | E13: 38178 | F13: 419229 | G13: 419000
B14: Exquisite jewellery | C14: 597406 | D14: 144037 | E14: 362484 | F14: 238034 | G14: 238000
B16: Horses | C16: 65000 | E16: 70000 | F16: 40000 | G16: 380000
C19: Questions to be solved : 1. Plot a graph to compare the sales of 2012, 2013, 2015 and 2016. 2. Calculate the total sales of all the years using a pivot table. 3. Compare the percentage contribution for differrent products in different years. 4. Compare and show the sales trends of Antiques and Fish Aquarium for all the years.

Sheet Clean sales data
B2: * This Sales dataset for different products is collected from a renowned store in Mumbai. * It should be used to answer all the questions correctly. * The dataset contains the names of different products and their selling prices for 5 years.
B5: Sales of 7 products across 5 years
B6: Products | C6: 2012 | D6: 2013 | E6: 2014 | F6: 2015 | G6: 2016
B7: Antiques | C7: 432521 | D7: 227724 | E7: 530619 | F7: 182911 | G7: 182000
B8: Bottles | C8: 44244 | D8: 310416 | E8: 123456 | F8: 92490 | G8: 921000
B9: Cars | C9: 433796 | D9: 191447 | E9: 18073 | F9: 484888 | G9: 484000
B10: Fish Aquarium | C10: 50000 | D10: 60000 | E10: 30000 | F10: 75120 | G10: 87494
B11: Drones | C11: 539770 | D11: 125314 | E11: 38178 | F11: 419229 | G11: 419000
B12: Exquisite jewellery | C12: 597406 | D12: 144037 | E12: 362484 | F12: 238034 | G12: 238000
B13: Horses | C13: 65000 | D13: 123456 | E13: 70000 | F13: 40000 | G13: 380000
B15: Questions to be solved : 1. Plot a graph to compare the sales of 2012, 2013, 2015 and 2016. 2. Calculate the total sales of all the years using a pivot table. 3. Compare the percentage contribution for differrent products in different years. 4. Compare and show the sales trends of Antiques and Fish Aquarium for all the years.

Sheet Dashboard_New
G21: Products | H21: 2012 Summary | I21: 2013 Summary | J21: 2014 Summary | K21: 2015 Summary | L21: 2016 Summary
G22: Antiques | H22: 432521 | I22: 227724 | J22: 530619 | K22: 182911 | L22: 182000
G23: Bottles | H23: 44244 | I23: 310416 | J23: 123456 | K23: 92490 | L23: 921000
G24: Cars | H24: 433796 | I24: 191447 | J24: 18073 | K24: 484888 | L24: 484000
G25: Drones | H25: 539770 | I25: 125314 | J25: 38178 | K25: 419229 | L25: 419000
G26: Exquisite jewellery | H26: 597406 | I26: 144037 | J26: 362484 | K26: 238034 | L26: 238000
G27: Fish Aquarium | H27: 50000 | I27: 60000 | J27: 30000 | K27: 75120 | L27: 87494
G28: Horses | H28: 65000 | I28: 123456 | J28: 70000 | K28: 38000 | L28: 380000
G29: Grand Total | H29: 2162737 | I29: 1182394 | J29: 1172810 | K29: 1530672 | L29: 2711494
